package com.loc;

import android.content.Context;
import android.text.TextUtils;
import java.io.File;
import java.security.PublicKey;
import java.security.cert.Certificate;
import java.util.Date;

final class be
  extends bc
{
  private PublicKey i;
  
  /* Error */
  be(final Context paramContext, v paramv)
    throws Exception
  {
    // Byte code:
    //   0: aload_0
    //   1: aload_1
    //   2: aload_2
    //   3: invokespecial 16	com/loc/bc:<init>	(Landroid/content/Context;Lcom/loc/v;)V
    //   6: aconst_null
    //   7: astore 4
    //   9: aconst_null
    //   10: astore_3
    //   11: aload_0
    //   12: aconst_null
    //   13: putfield 18	com/loc/be:i	Ljava/security/PublicKey;
    //   16: aload_1
    //   17: aload_2
    //   18: invokevirtual 24	com/loc/v:a	()Ljava/lang/String;
    //   21: aload_2
    //   22: invokevirtual 27	com/loc/v:b	()Ljava/lang/String;
    //   25: invokestatic 32	com/loc/av:b	(Landroid/content/Context;Ljava/lang/String;Ljava/lang/String;)Ljava/lang/String;
    //   28: astore 5
    //   30: aload_1
    //   31: invokestatic 35	com/loc/av:a	(Landroid/content/Context;)Ljava/lang/String;
    //   34: astore 6
    //   36: aload 5
    //   38: invokestatic 41	android/text/TextUtils:isEmpty	(Ljava/lang/CharSequence;)Z
    //   41: ifne +271 -> 312
    //   44: aload 6
    //   46: invokestatic 41	android/text/TextUtils:isEmpty	(Ljava/lang/CharSequence;)Z
    //   49: ifne +263 -> 312
    //   52: new 43	java/io/File
    //   55: dup
    //   56: aload 5
    //   58: invokespecial 46	java/io/File:<init>	(Ljava/lang/String;)V
    //   61: astore_2
    //   62: invokestatic 51	com/loc/ba:b	()Lcom/loc/ba;
    //   65: aload_0
    //   66: getfield 55	com/loc/be:e	Lcom/loc/v;
    //   69: invokevirtual 58	com/loc/ba:a	(Lcom/loc/v;)Lcom/loc/ba$a;
    //   72: getfield 63	com/loc/ba$a:b	Z
    //   75: ifne +227 -> 302
    //   78: new 65	java/lang/StringBuilder
    //   81: dup
    //   82: invokespecial 68	java/lang/StringBuilder:<init>	()V
    //   85: astore 7
    //   87: aload 7
    //   89: aload 6
    //   91: invokevirtual 72	java/lang/StringBuilder:append	(Ljava/lang/String;)Ljava/lang/StringBuilder;
    //   94: pop
    //   95: aload 7
    //   97: getstatic 76	java/io/File:separator	Ljava/lang/String;
    //   100: invokevirtual 72	java/lang/StringBuilder:append	(Ljava/lang/String;)Ljava/lang/StringBuilder;
    //   103: pop
    //   104: aload 7
    //   106: aload_2
    //   107: invokevirtual 79	java/io/File:getName	()Ljava/lang/String;
    //   110: invokestatic 82	com/loc/av:a	(Ljava/lang/String;)Ljava/lang/String;
    //   113: invokevirtual 72	java/lang/StringBuilder:append	(Ljava/lang/String;)Ljava/lang/StringBuilder;
    //   116: pop
    //   117: aload 7
    //   119: invokevirtual 85	java/lang/StringBuilder:toString	()Ljava/lang/String;
    //   122: astore 7
    //   124: aload_3
    //   125: astore_2
    //   126: aload_0
    //   127: getfield 89	com/loc/be:c	Ldalvik/system/DexFile;
    //   130: ifnull +6 -> 136
    //   133: goto +76 -> 209
    //   136: aload_3
    //   137: astore_2
    //   138: invokestatic 51	com/loc/ba:b	()Lcom/loc/ba;
    //   141: aload_0
    //   142: getfield 55	com/loc/be:e	Lcom/loc/v;
    //   145: invokevirtual 58	com/loc/ba:a	(Lcom/loc/v;)Lcom/loc/ba$a;
    //   148: astore_3
    //   149: aload_3
    //   150: ifnull +11 -> 161
    //   153: aload_3
    //   154: iconst_1
    //   155: putfield 91	com/loc/ba$a:a	Z
    //   158: goto +3 -> 161
    //   161: aload_0
    //   162: invokevirtual 93	com/loc/be:b	()V
    //   165: aload_3
    //   166: getfield 63	com/loc/ba$a:b	Z
    //   169: ifne +66 -> 235
    //   172: aload_0
    //   173: aload 5
    //   175: aload 7
    //   177: iconst_0
    //   178: invokestatic 99	dalvik/system/DexFile:loadDex	(Ljava/lang/String;Ljava/lang/String;I)Ldalvik/system/DexFile;
    //   181: putfield 89	com/loc/be:c	Ldalvik/system/DexFile;
    //   184: aload_3
    //   185: ifnull +24 -> 209
    //   188: aload_3
    //   189: iconst_0
    //   190: putfield 91	com/loc/ba$a:a	Z
    //   193: aload_3
    //   194: monitorenter
    //   195: aload_3
    //   196: invokevirtual 104	java/lang/Object:notify	()V
    //   199: aload_3
    //   200: monitorexit
    //   201: goto +8 -> 209
    //   204: astore_2
    //   205: aload_3
    //   206: monitorexit
    //   207: aload_2
    //   208: athrow
    //   209: invokestatic 51	com/loc/ba:b	()Lcom/loc/ba;
    //   212: invokevirtual 107	com/loc/ba:a	()Ljava/util/concurrent/ExecutorService;
    //   215: new 6	com/loc/be$1
    //   218: dup
    //   219: aload_0
    //   220: aload_1
    //   221: aload 5
    //   223: aload 6
    //   225: invokespecial 110	com/loc/be$1:<init>	(Lcom/loc/be;Landroid/content/Context;Ljava/lang/String;Ljava/lang/String;)V
    //   228: invokeinterface 116 2 0
    //   233: pop
    //   234: return
    //   235: new 12	java/lang/Exception
    //   238: dup
    //   239: ldc 118
    //   241: invokespecial 119	java/lang/Exception:<init>	(Ljava/lang/String;)V
    //   244: athrow
    //   245: astore_1
    //   246: goto +29 -> 275
    //   249: astore_3
    //   250: aload 4
    //   252: astore_1
    //   253: aload_1
    //   254: astore_2
    //   255: aload_3
    //   256: ldc 121
    //   258: ldc 123
    //   260: invokestatic 128	com/loc/ag:a	(Ljava/lang/Throwable;Ljava/lang/String;Ljava/lang/String;)V
    //   263: aload_1
    //   264: astore_2
    //   265: new 12	java/lang/Exception
    //   268: dup
    //   269: ldc -126
    //   271: invokespecial 119	java/lang/Exception:<init>	(Ljava/lang/String;)V
    //   274: athrow
    //   275: aload_2
    //   276: ifnull +24 -> 300
    //   279: aload_2
    //   280: iconst_0
    //   281: putfield 91	com/loc/ba$a:a	Z
    //   284: aload_2
    //   285: monitorenter
    //   286: aload_2
    //   287: invokevirtual 104	java/lang/Object:notify	()V
    //   290: aload_2
    //   291: monitorexit
    //   292: goto +8 -> 300
    //   295: astore_3
    //   296: aload_2
    //   297: monitorexit
    //   298: aload_3
    //   299: athrow
    //   300: aload_1
    //   301: athrow
    //   302: new 12	java/lang/Exception
    //   305: dup
    //   306: ldc 118
    //   308: invokespecial 119	java/lang/Exception:<init>	(Ljava/lang/String;)V
    //   311: athrow
    //   312: new 12	java/lang/Exception
    //   315: dup
    //   316: ldc -124
    //   318: invokespecial 119	java/lang/Exception:<init>	(Ljava/lang/String;)V
    //   321: athrow
    //   322: astore_2
    //   323: goto -114 -> 209
    //   326: astore_1
    //   327: return
    //   328: astore_2
    //   329: goto -29 -> 300
    //   332: astore_1
    //   333: aload_3
    //   334: astore_2
    //   335: goto -60 -> 275
    //   338: astore_2
    //   339: aload_3
    //   340: astore_1
    //   341: aload_2
    //   342: astore_3
    //   343: goto -90 -> 253
    // Local variable table:
    //   start	length	slot	name	signature
    //   0	346	0	this	be
    //   0	346	1	paramContext	Context
    //   0	346	2	paramv	v
    //   10	196	3	locala	ba.a
    //   249	7	3	localThrowable	Throwable
    //   295	45	3	localObject1	Object
    //   342	1	3	localv	v
    //   7	244	4	localObject2	Object
    //   28	194	5	str1	String
    //   34	190	6	str2	String
    //   85	91	7	localObject3	Object
    // Exception table:
    //   from	to	target	type
    //   195	201	204	finally
    //   205	207	204	finally
    //   126	133	245	finally
    //   138	149	245	finally
    //   255	263	245	finally
    //   265	275	245	finally
    //   126	133	249	java/lang/Throwable
    //   138	149	249	java/lang/Throwable
    //   286	292	295	finally
    //   296	298	295	finally
    //   188	195	322	java/lang/Throwable
    //   207	209	322	java/lang/Throwable
    //   209	234	326	java/lang/Throwable
    //   279	286	328	java/lang/Throwable
    //   298	300	328	java/lang/Throwable
    //   153	158	332	finally
    //   161	184	332	finally
    //   235	245	332	finally
    //   153	158	338	java/lang/Throwable
    //   161	184	338	java/lang/Throwable
    //   235	245	338	java/lang/Throwable
  }
  
  /* Error */
  private static void a(java.util.jar.JarFile paramJarFile, java.util.jar.JarEntry paramJarEntry)
    throws java.io.IOException
  {
    // Byte code:
    //   0: aconst_null
    //   1: astore 4
    //   3: aconst_null
    //   4: astore_3
    //   5: aload_0
    //   6: aload_1
    //   7: invokevirtual 143	java/util/jar/JarFile:getInputStream	(Ljava/util/zip/ZipEntry;)Ljava/io/InputStream;
    //   10: astore_0
    //   11: sipush 8192
    //   14: newarray <illegal type>
    //   16: astore_1
    //   17: aload_0
    //   18: aload_1
    //   19: invokevirtual 149	java/io/InputStream:read	([B)I
    //   22: istore_2
    //   23: iload_2
    //   24: ifgt -7 -> 17
    //   27: aload_0
    //   28: invokestatic 154	com/loc/bb:a	(Ljava/io/Closeable;)V
    //   31: return
    //   32: astore_0
    //   33: aload_0
    //   34: invokevirtual 157	java/lang/Throwable:printStackTrace	()V
    //   37: return
    //   38: astore_1
    //   39: aload_0
    //   40: astore_3
    //   41: aload_1
    //   42: astore_0
    //   43: goto +36 -> 79
    //   46: astore_1
    //   47: goto +11 -> 58
    //   50: astore_0
    //   51: goto +28 -> 79
    //   54: astore_1
    //   55: aload 4
    //   57: astore_0
    //   58: aload_0
    //   59: astore_3
    //   60: aload_1
    //   61: ldc -97
    //   63: ldc -95
    //   65: invokestatic 128	com/loc/ag:a	(Ljava/lang/Throwable;Ljava/lang/String;Ljava/lang/String;)V
    //   68: aload_0
    //   69: invokestatic 154	com/loc/bb:a	(Ljava/io/Closeable;)V
    //   72: return
    //   73: astore_0
    //   74: aload_0
    //   75: invokevirtual 157	java/lang/Throwable:printStackTrace	()V
    //   78: return
    //   79: aload_3
    //   80: invokestatic 154	com/loc/bb:a	(Ljava/io/Closeable;)V
    //   83: goto +8 -> 91
    //   86: astore_1
    //   87: aload_1
    //   88: invokevirtual 157	java/lang/Throwable:printStackTrace	()V
    //   91: aload_0
    //   92: athrow
    // Local variable table:
    //   start	length	slot	name	signature
    //   0	93	0	paramJarFile	java.util.jar.JarFile
    //   0	93	1	paramJarEntry	java.util.jar.JarEntry
    //   22	2	2	j	int
    //   4	76	3	localJarFile	java.util.jar.JarFile
    //   1	55	4	localObject	Object
    // Exception table:
    //   from	to	target	type
    //   27	31	32	java/lang/Throwable
    //   11	17	38	finally
    //   17	23	38	finally
    //   11	17	46	java/lang/Throwable
    //   17	23	46	java/lang/Throwable
    //   5	11	50	finally
    //   60	68	50	finally
    //   5	11	54	java/lang/Throwable
    //   68	72	73	java/lang/Throwable
    //   79	83	86	java/lang/Throwable
  }
  
  /* Error */
  private boolean a(File paramFile)
  {
    // Byte code:
    //   0: aconst_null
    //   1: astore 5
    //   3: aconst_null
    //   4: astore 4
    //   6: aload 4
    //   8: astore_3
    //   9: aload_0
    //   10: getfield 18	com/loc/be:i	Ljava/security/PublicKey;
    //   13: ifnonnull +13 -> 26
    //   16: aload 4
    //   18: astore_3
    //   19: aload_0
    //   20: invokestatic 165	com/loc/bb:a	()Ljava/security/PublicKey;
    //   23: putfield 18	com/loc/be:i	Ljava/security/PublicKey;
    //   26: aload 4
    //   28: astore_3
    //   29: new 139	java/util/jar/JarFile
    //   32: dup
    //   33: aload_1
    //   34: invokespecial 168	java/util/jar/JarFile:<init>	(Ljava/io/File;)V
    //   37: astore_1
    //   38: aload_1
    //   39: ldc -86
    //   41: invokevirtual 174	java/util/jar/JarFile:getJarEntry	(Ljava/lang/String;)Ljava/util/jar/JarEntry;
    //   44: astore_3
    //   45: aload_3
    //   46: ifnonnull +9 -> 55
    //   49: aload_1
    //   50: invokevirtual 177	java/util/jar/JarFile:close	()V
    //   53: iconst_0
    //   54: ireturn
    //   55: aload_1
    //   56: aload_3
    //   57: invokestatic 179	com/loc/be:a	(Ljava/util/jar/JarFile;Ljava/util/jar/JarEntry;)V
    //   60: aload_3
    //   61: invokevirtual 185	java/util/jar/JarEntry:getCertificates	()[Ljava/security/cert/Certificate;
    //   64: astore_3
    //   65: aload_3
    //   66: ifnonnull +9 -> 75
    //   69: aload_1
    //   70: invokevirtual 177	java/util/jar/JarFile:close	()V
    //   73: iconst_0
    //   74: ireturn
    //   75: aload_0
    //   76: aload_3
    //   77: invokespecial 188	com/loc/be:a	([Ljava/security/cert/Certificate;)Z
    //   80: istore_2
    //   81: aload_1
    //   82: invokevirtual 177	java/util/jar/JarFile:close	()V
    //   85: iload_2
    //   86: ireturn
    //   87: astore 4
    //   89: aload_1
    //   90: astore_3
    //   91: aload 4
    //   93: astore_1
    //   94: goto +38 -> 132
    //   97: astore 4
    //   99: goto +12 -> 111
    //   102: astore_1
    //   103: goto +29 -> 132
    //   106: astore 4
    //   108: aload 5
    //   110: astore_1
    //   111: aload_1
    //   112: astore_3
    //   113: aload 4
    //   115: ldc -97
    //   117: ldc -66
    //   119: invokestatic 128	com/loc/ag:a	(Ljava/lang/Throwable;Ljava/lang/String;Ljava/lang/String;)V
    //   122: aload_1
    //   123: ifnull +7 -> 130
    //   126: aload_1
    //   127: invokevirtual 177	java/util/jar/JarFile:close	()V
    //   130: iconst_0
    //   131: ireturn
    //   132: aload_3
    //   133: ifnull +7 -> 140
    //   136: aload_3
    //   137: invokevirtual 177	java/util/jar/JarFile:close	()V
    //   140: aload_1
    //   141: athrow
    //   142: astore_1
    //   143: iconst_0
    //   144: ireturn
    //   145: astore_1
    //   146: iconst_0
    //   147: ireturn
    //   148: astore_1
    //   149: iload_2
    //   150: ireturn
    //   151: astore_1
    //   152: iconst_0
    //   153: ireturn
    //   154: astore_3
    //   155: goto -15 -> 140
    // Local variable table:
    //   start	length	slot	name	signature
    //   0	158	0	this	be
    //   0	158	1	paramFile	File
    //   80	70	2	bool	boolean
    //   8	129	3	localObject1	Object
    //   154	1	3	localThrowable1	Throwable
    //   4	23	4	localObject2	Object
    //   87	5	4	localObject3	Object
    //   97	1	4	localThrowable2	Throwable
    //   106	8	4	localThrowable3	Throwable
    //   1	108	5	localObject4	Object
    // Exception table:
    //   from	to	target	type
    //   38	45	87	finally
    //   55	65	87	finally
    //   75	81	87	finally
    //   38	45	97	java/lang/Throwable
    //   55	65	97	java/lang/Throwable
    //   75	81	97	java/lang/Throwable
    //   9	16	102	finally
    //   19	26	102	finally
    //   29	38	102	finally
    //   113	122	102	finally
    //   9	16	106	java/lang/Throwable
    //   19	26	106	java/lang/Throwable
    //   29	38	106	java/lang/Throwable
    //   49	53	142	java/lang/Throwable
    //   69	73	145	java/lang/Throwable
    //   81	85	148	java/lang/Throwable
    //   126	130	151	java/lang/Throwable
    //   136	140	154	java/lang/Throwable
  }
  
  private boolean a(Certificate[] paramArrayOfCertificate)
  {
    try
    {
      if (paramArrayOfCertificate.length > 0)
      {
        int j = paramArrayOfCertificate.length - 1;
        if (j >= 0)
        {
          paramArrayOfCertificate[j].verify(this.i);
          return true;
        }
      }
    }
    catch (Exception paramArrayOfCertificate)
    {
      ag.a(paramArrayOfCertificate, "DyLoader", "check");
    }
    return false;
  }
  
  final void a(Context paramContext, String paramString1, String paramString2)
    throws Exception
  {
    new Date().getTime();
    for (;;)
    {
      try
      {
        paramContext = new an(paramContext, ax.b());
        paramString1 = new File(paramString1);
        Object localObject = av.a.a(paramContext, paramString1.getName());
        if (localObject != null) {
          this.f = ((ay)localObject).e();
        }
        localObject = this.e;
        String str = paramString1.getAbsolutePath();
        bool = a(new File(str));
        j = 0;
        if (!bool) {
          break label393;
        }
        bool = bb.a(paramContext, av.a(this.a, ((v)localObject).a(), ((v)localObject).b()), str, (v)localObject);
        if (!bool)
        {
          this.d = false;
          av.a(this.a, paramContext, paramString1.getName());
          localObject = av.a(this.a, paramContext, this.e);
          if (!TextUtils.isEmpty((CharSequence)localObject))
          {
            this.f = ((String)localObject);
            av.a(this.a, this.e);
          }
        }
        if (!paramString1.exists()) {
          return;
        }
        localObject = new StringBuilder();
        ((StringBuilder)localObject).append(paramString2);
        ((StringBuilder)localObject).append(File.separator);
        ((StringBuilder)localObject).append(av.a(paramString1.getName()));
        if (new File(((StringBuilder)localObject).toString()).exists())
        {
          paramString1 = av.a(paramString1.getName());
          paramString2 = this.f;
          localObject = av.a(this.a, paramString1);
          if (bb.a(paramContext, paramString1, (String)localObject, this.e)) {
            break label399;
          }
          if (av.a.a(paramContext, paramString1) == null)
          {
            if (TextUtils.isEmpty(this.f)) {
              break label399;
            }
            paramContext.a(new ay.a(paramString1, s.a((String)localObject), this.e.a(), this.e.b(), paramString2).a("useod").a(), ay.b(paramString1));
            break label399;
          }
          if (j == 0) {
            av.a(this.a, this.e);
          }
        }
      }
      catch (Throwable paramContext)
      {
        ag.a(paramContext, "dLoader", "verifyD()");
      }
      new Date().getTime();
      return;
      label393:
      boolean bool = false;
      continue;
      label399:
      int j = 1;
    }
  }
  
  /* Error */
  protected final Class<?> findClass(String paramString)
    throws java.lang.ClassNotFoundException
  {
    // Byte code:
    //   0: aload_0
    //   1: getfield 89	com/loc/be:c	Ldalvik/system/DexFile;
    //   4: astore_2
    //   5: aload_2
    //   6: ifnull +201 -> 207
    //   9: aconst_null
    //   10: astore 4
    //   12: aconst_null
    //   13: astore_3
    //   14: aload 4
    //   16: astore_2
    //   17: aload_0
    //   18: getfield 288	com/loc/be:b	Ljava/util/Map;
    //   21: astore 5
    //   23: aload 4
    //   25: astore_2
    //   26: aload 5
    //   28: monitorenter
    //   29: aload_0
    //   30: getfield 288	com/loc/be:b	Ljava/util/Map;
    //   33: aload_1
    //   34: invokeinterface 294 2 0
    //   39: checkcast 296	java/lang/Class
    //   42: astore_2
    //   43: aload 5
    //   45: monitorexit
    //   46: goto +32 -> 78
    //   49: astore_3
    //   50: aload_3
    //   51: astore 4
    //   53: goto +7 -> 60
    //   56: astore 4
    //   58: aload_3
    //   59: astore_2
    //   60: aload_2
    //   61: astore_3
    //   62: aload 5
    //   64: monitorexit
    //   65: aload 4
    //   67: athrow
    //   68: astore_3
    //   69: aload_3
    //   70: ldc 121
    //   72: ldc_w 298
    //   75: invokestatic 128	com/loc/ag:a	(Ljava/lang/Throwable;Ljava/lang/String;Ljava/lang/String;)V
    //   78: aload_2
    //   79: ifnull +10 -> 89
    //   82: aload_0
    //   83: iconst_0
    //   84: putfield 301	com/loc/be:h	Z
    //   87: aload_2
    //   88: areturn
    //   89: aload_0
    //   90: getfield 304	com/loc/be:g	Z
    //   93: ifne +105 -> 198
    //   96: aload_0
    //   97: iconst_1
    //   98: putfield 301	com/loc/be:h	Z
    //   101: aload_0
    //   102: getfield 89	com/loc/be:c	Ldalvik/system/DexFile;
    //   105: aload_1
    //   106: aload_0
    //   107: invokevirtual 308	dalvik/system/DexFile:loadClass	(Ljava/lang/String;Ljava/lang/ClassLoader;)Ljava/lang/Class;
    //   110: astore_2
    //   111: aload_0
    //   112: getfield 89	com/loc/be:c	Ldalvik/system/DexFile;
    //   115: astore_3
    //   116: aload_3
    //   117: monitorenter
    //   118: aload_0
    //   119: getfield 89	com/loc/be:c	Ldalvik/system/DexFile;
    //   122: invokevirtual 104	java/lang/Object:notify	()V
    //   125: aload_3
    //   126: monitorexit
    //   127: aload_0
    //   128: iconst_0
    //   129: putfield 301	com/loc/be:h	Z
    //   132: aload_2
    //   133: ifnull +51 -> 184
    //   136: aload_0
    //   137: getfield 288	com/loc/be:b	Ljava/util/Map;
    //   140: astore_3
    //   141: aload_3
    //   142: monitorenter
    //   143: aload_0
    //   144: getfield 288	com/loc/be:b	Ljava/util/Map;
    //   147: aload_1
    //   148: aload_2
    //   149: invokeinterface 312 3 0
    //   154: pop
    //   155: aload_3
    //   156: monitorexit
    //   157: goto +20 -> 177
    //   160: astore 4
    //   162: aload_3
    //   163: monitorexit
    //   164: aload 4
    //   166: athrow
    //   167: astore_3
    //   168: aload_3
    //   169: ldc 121
    //   171: ldc_w 298
    //   174: invokestatic 128	com/loc/ag:a	(Ljava/lang/Throwable;Ljava/lang/String;Ljava/lang/String;)V
    //   177: aload_0
    //   178: iconst_0
    //   179: putfield 301	com/loc/be:h	Z
    //   182: aload_2
    //   183: areturn
    //   184: new 285	java/lang/ClassNotFoundException
    //   187: dup
    //   188: aload_1
    //   189: invokespecial 313	java/lang/ClassNotFoundException:<init>	(Ljava/lang/String;)V
    //   192: athrow
    //   193: astore_2
    //   194: aload_3
    //   195: monitorexit
    //   196: aload_2
    //   197: athrow
    //   198: new 285	java/lang/ClassNotFoundException
    //   201: dup
    //   202: aload_1
    //   203: invokespecial 313	java/lang/ClassNotFoundException:<init>	(Ljava/lang/String;)V
    //   206: athrow
    //   207: new 285	java/lang/ClassNotFoundException
    //   210: dup
    //   211: aload_1
    //   212: invokespecial 313	java/lang/ClassNotFoundException:<init>	(Ljava/lang/String;)V
    //   215: athrow
    //   216: astore_1
    //   217: goto +25 -> 242
    //   220: astore_2
    //   221: aload_2
    //   222: ldc 121
    //   224: ldc_w 298
    //   227: invokestatic 128	com/loc/ag:a	(Ljava/lang/Throwable;Ljava/lang/String;Ljava/lang/String;)V
    //   230: new 285	java/lang/ClassNotFoundException
    //   233: dup
    //   234: aload_1
    //   235: invokespecial 313	java/lang/ClassNotFoundException:<init>	(Ljava/lang/String;)V
    //   238: athrow
    //   239: astore_1
    //   240: aload_1
    //   241: athrow
    //   242: aload_0
    //   243: iconst_0
    //   244: putfield 301	com/loc/be:h	Z
    //   247: aload_1
    //   248: athrow
    // Local variable table:
    //   start	length	slot	name	signature
    //   0	249	0	this	be
    //   0	249	1	paramString	String
    //   4	179	2	localObject1	Object
    //   193	4	2	localObject2	Object
    //   220	2	2	localThrowable1	Throwable
    //   13	1	3	localObject3	Object
    //   49	10	3	localObject4	Object
    //   61	1	3	localObject5	Object
    //   68	2	3	localThrowable2	Throwable
    //   167	28	3	localThrowable3	Throwable
    //   10	42	4	localObject7	Object
    //   56	10	4	localObject8	Object
    //   160	5	4	localObject9	Object
    //   21	42	5	localMap	java.util.Map
    // Exception table:
    //   from	to	target	type
    //   43	46	49	finally
    //   29	43	56	finally
    //   62	65	56	finally
    //   17	23	68	java/lang/Throwable
    //   26	29	68	java/lang/Throwable
    //   65	68	68	java/lang/Throwable
    //   143	157	160	finally
    //   162	164	160	finally
    //   136	143	167	java/lang/Throwable
    //   164	167	167	java/lang/Throwable
    //   118	127	193	finally
    //   194	196	193	finally
    //   0	5	216	finally
    //   17	23	216	finally
    //   26	29	216	finally
    //   65	68	216	finally
    //   69	78	216	finally
    //   89	118	216	finally
    //   127	132	216	finally
    //   136	143	216	finally
    //   164	167	216	finally
    //   168	177	216	finally
    //   184	193	216	finally
    //   196	198	216	finally
    //   198	207	216	finally
    //   207	216	216	finally
    //   221	239	216	finally
    //   240	242	216	finally
    //   0	5	220	java/lang/Throwable
    //   69	78	220	java/lang/Throwable
    //   89	118	220	java/lang/Throwable
    //   127	132	220	java/lang/Throwable
    //   168	177	220	java/lang/Throwable
    //   184	193	220	java/lang/Throwable
    //   196	198	220	java/lang/Throwable
    //   198	207	220	java/lang/Throwable
    //   207	216	220	java/lang/Throwable
    //   0	5	239	java/lang/ClassNotFoundException
    //   17	23	239	java/lang/ClassNotFoundException
    //   26	29	239	java/lang/ClassNotFoundException
    //   65	68	239	java/lang/ClassNotFoundException
    //   69	78	239	java/lang/ClassNotFoundException
    //   89	118	239	java/lang/ClassNotFoundException
    //   127	132	239	java/lang/ClassNotFoundException
    //   136	143	239	java/lang/ClassNotFoundException
    //   164	167	239	java/lang/ClassNotFoundException
    //   168	177	239	java/lang/ClassNotFoundException
    //   184	193	239	java/lang/ClassNotFoundException
    //   196	198	239	java/lang/ClassNotFoundException
    //   198	207	239	java/lang/ClassNotFoundException
    //   207	216	239	java/lang/ClassNotFoundException
  }
}


/* Location:              C:\Users\lixia\Desktop\android反编译三件套\dex2jar-2.0\classes-dex2jar.jar!\com\loc\be.class
 * Java compiler version: 6 (50.0)
 * JD-Core Version:       0.7.1
 */