package com.loc;

import android.content.Context;
import android.os.Build;
import android.os.Build.VERSION;
import android.text.TextUtils;
import java.net.URLDecoder;
import java.util.HashMap;
import java.util.Map;
import org.json.JSONException;
import org.json.JSONObject;

public final class m
{
  public static int a = -1;
  public static String b = "";
  
  public static a a(Context paramContext, v paramv, String paramString, boolean paramBoolean)
  {
    return b(paramContext, paramv, paramString, paramBoolean);
  }
  
  private static String a(JSONObject paramJSONObject, String paramString)
    throws JSONException
  {
    if (paramJSONObject == null) {
      return "";
    }
    String str2 = "";
    String str1 = str2;
    if (paramJSONObject.has(paramString))
    {
      str1 = str2;
      if (!paramJSONObject.getString(paramString).equals("[]")) {
        str1 = paramJSONObject.optString(paramString);
      }
    }
    return str1;
  }
  
  private static void a(Context paramContext, v paramv, String paramString)
  {
    HashMap localHashMap = new HashMap();
    localHashMap.put("amap_sdk_auth_fail", "1");
    localHashMap.put("amap_sdk_auth_fail_type", paramString);
    localHashMap.put("amap_sdk_name", paramv.a());
    localHashMap.put("amap_sdk_version", paramv.c());
    paramv = new JSONObject(localHashMap).toString();
    if (TextUtils.isEmpty(paramv)) {
      return;
    }
    try
    {
      paramString = new bu(paramContext, "core", "1.0", "O001");
      paramString.a(paramv);
      bv.a(paramString, paramContext);
      return;
    }
    catch (k paramContext) {}
  }
  
  private static void a(Context paramContext, v paramv, Throwable paramThrowable)
  {
    a(paramContext, paramv, paramThrowable.getMessage());
  }
  
  public static void a(Context paramContext, String paramString)
  {
    l.a(paramContext, paramString);
  }
  
  private static void a(a parama, JSONObject paramJSONObject)
  {
    try
    {
      if (w.a(paramJSONObject, "11B")) {
        parama.h = paramJSONObject.getJSONObject("11B");
      }
      if (w.a(paramJSONObject, "11C")) {
        parama.k = paramJSONObject.getJSONObject("11C");
      }
      if (w.a(paramJSONObject, "11I")) {
        parama.l = paramJSONObject.getJSONObject("11I");
      }
      if (w.a(paramJSONObject, "11H")) {
        parama.m = paramJSONObject.getJSONObject("11H");
      }
      if (w.a(paramJSONObject, "11E")) {
        parama.n = paramJSONObject.getJSONObject("11E");
      }
      if (w.a(paramJSONObject, "11F")) {
        parama.o = paramJSONObject.getJSONObject("11F");
      }
      if (w.a(paramJSONObject, "13A")) {
        parama.q = paramJSONObject.getJSONObject("13A");
      }
      if (w.a(paramJSONObject, "13J")) {
        parama.i = paramJSONObject.getJSONObject("13J");
      }
      if (w.a(paramJSONObject, "11G")) {
        parama.p = paramJSONObject.getJSONObject("11G");
      }
      if (w.a(paramJSONObject, "006")) {
        parama.r = paramJSONObject.getJSONObject("006");
      }
      if (w.a(paramJSONObject, "010")) {
        parama.s = paramJSONObject.getJSONObject("010");
      }
      JSONObject localJSONObject;
      m.a.b localb;
      if (w.a(paramJSONObject, "11Z"))
      {
        localJSONObject = paramJSONObject.getJSONObject("11Z");
        localb = new m.a.b();
        a(localJSONObject, localb);
        parama.C = localb;
      }
      if (w.a(paramJSONObject, "135")) {
        parama.j = paramJSONObject.getJSONObject("135");
      }
      if (w.a(paramJSONObject, "13S")) {
        parama.g = paramJSONObject.getJSONObject("13S");
      }
      if (w.a(paramJSONObject, "121"))
      {
        localJSONObject = paramJSONObject.getJSONObject("121");
        localb = new m.a.b();
        a(localJSONObject, localb);
        parama.D = localb;
      }
      if (w.a(paramJSONObject, "122"))
      {
        localJSONObject = paramJSONObject.getJSONObject("122");
        localb = new m.a.b();
        a(localJSONObject, localb);
        parama.E = localb;
      }
      if (w.a(paramJSONObject, "123"))
      {
        localJSONObject = paramJSONObject.getJSONObject("123");
        localb = new m.a.b();
        a(localJSONObject, localb);
        parama.F = localb;
      }
      if (w.a(paramJSONObject, "011")) {
        parama.c = paramJSONObject.getJSONObject("011");
      }
      if (w.a(paramJSONObject, "012")) {
        parama.d = paramJSONObject.getJSONObject("012");
      }
      if (w.a(paramJSONObject, "013")) {
        parama.e = paramJSONObject.getJSONObject("013");
      }
      if (w.a(paramJSONObject, "014")) {
        parama.f = paramJSONObject.getJSONObject("014");
      }
      if (w.a(paramJSONObject, "145")) {
        parama.t = paramJSONObject.getJSONObject("145");
      }
      if (w.a(paramJSONObject, "14B")) {
        parama.u = paramJSONObject.getJSONObject("14B");
      }
      if (w.a(paramJSONObject, "14D")) {
        parama.v = paramJSONObject.getJSONObject("14D");
      }
      return;
    }
    catch (Throwable parama)
    {
      aj.b(parama, "at", "pe");
    }
  }
  
  private static void a(String paramString, a parama, JSONObject paramJSONObject)
    throws JSONException
  {
    Object localObject1 = new m.a.a();
    ((m.a.a)localObject1).a = false;
    ((m.a.a)localObject1).b = false;
    parama.x = ((m.a.a)localObject1);
    try
    {
      paramString = paramString.split(";");
      String str1;
      if ((paramString != null) && (paramString.length > 0))
      {
        int j = paramString.length;
        int i = 0;
        while (i < j)
        {
          str1 = paramString[i];
          if (paramJSONObject.has(str1)) {
            parama.w.putOpt(str1, paramJSONObject.get(str1));
          }
          i += 1;
        }
      }
      Object localObject3;
      Object localObject2;
      Object localObject4;
      String str2;
      String str3;
      m.a.f localf;
      return;
    }
    catch (Throwable paramString)
    {
      ag.a(paramString, "at", "co");
      if (w.a(paramJSONObject, "16H")) {
        a.a(parama, a(paramJSONObject.getJSONObject("16H").optString("able"), false));
      }
      if (w.a(paramJSONObject, "11K")) {
        try
        {
          paramString = paramJSONObject.getJSONObject("11K");
          ((m.a.a)localObject1).a = a(paramString.getString("able"), false);
          if (paramString.has("off")) {
            ((m.a.a)localObject1).c = paramString.getJSONObject("off");
          }
        }
        catch (Throwable paramString)
        {
          ag.a(paramString, "AuthConfigManager", "loadException");
        }
      }
      if (w.a(paramJSONObject, "001"))
      {
        localObject3 = paramJSONObject.getJSONObject("001");
        paramString = new m.a.d();
        if (localObject3 != null) {
          try
          {
            localObject1 = a((JSONObject)localObject3, "md5");
            str1 = a((JSONObject)localObject3, "url");
            localObject3 = a((JSONObject)localObject3, "sdkversion");
            if ((!TextUtils.isEmpty((CharSequence)localObject1)) && (!TextUtils.isEmpty(str1)) && (!TextUtils.isEmpty((CharSequence)localObject3)))
            {
              paramString.a = str1;
              paramString.b = ((String)localObject1);
              paramString.c = ((String)localObject3);
            }
          }
          catch (Throwable localThrowable1)
          {
            ag.a(localThrowable1, "at", "psu");
          }
        }
        parama.y = paramString;
      }
      if (w.a(paramJSONObject, "002"))
      {
        paramString = paramJSONObject.getJSONObject("002");
        localObject2 = new m.a.c();
        a(paramString, (m.a.c)localObject2);
        parama.A = ((m.a.c)localObject2);
      }
      if (w.a(paramJSONObject, "14S"))
      {
        paramString = paramJSONObject.getJSONObject("14S");
        localObject2 = new m.a.c();
        a(paramString, (m.a.c)localObject2);
        parama.B = ((m.a.c)localObject2);
      }
      a(parama, paramJSONObject);
      if (w.a(paramJSONObject, "14Z"))
      {
        localObject4 = paramJSONObject.getJSONObject("14Z");
        paramString = new m.a.e();
        try
        {
          localObject2 = a((JSONObject)localObject4, "md5");
          str1 = a((JSONObject)localObject4, "md5info");
          localObject3 = a((JSONObject)localObject4, "url");
          str2 = a((JSONObject)localObject4, "able");
          str3 = a((JSONObject)localObject4, "on");
          localObject4 = a((JSONObject)localObject4, "mobileable");
          paramString.e = ((String)localObject2);
          paramString.f = str1;
          paramString.d = ((String)localObject3);
          paramString.a = a(str2, false);
          paramString.b = a(str3, false);
          paramString.c = a((String)localObject4, false);
        }
        catch (Throwable localThrowable2)
        {
          ag.a(localThrowable2, "at", "pes");
        }
        parama.G = paramString;
      }
      if (w.a(paramJSONObject, "151"))
      {
        paramString = paramJSONObject.getJSONObject("151");
        localf = new m.a.f();
        if (paramString != null) {
          localf.a = a(paramString.optString("able"), false);
        }
        parama.z = localf;
      }
      a(parama, paramJSONObject);
    }
  }
  
  private static void a(JSONObject paramJSONObject, m.a.b paramb)
  {
    try
    {
      String str1 = a(paramJSONObject, "m");
      String str2 = a(paramJSONObject, "u");
      String str3 = a(paramJSONObject, "v");
      String str4 = a(paramJSONObject, "able");
      paramJSONObject = a(paramJSONObject, "on");
      paramb.c = str1;
      paramb.b = str2;
      paramb.d = str3;
      paramb.a = a(str4, false);
      paramb.e = a(paramJSONObject, true);
      return;
    }
    catch (Throwable paramJSONObject)
    {
      ag.a(paramJSONObject, "at", "pe");
    }
  }
  
  private static void a(JSONObject paramJSONObject, m.a.c paramc)
  {
    if (paramJSONObject != null) {
      try
      {
        String str = a(paramJSONObject, "md5");
        paramJSONObject = a(paramJSONObject, "url");
        paramc.b = str;
        paramc.a = paramJSONObject;
        return;
      }
      catch (Throwable paramJSONObject)
      {
        ag.a(paramJSONObject, "at", "psc");
      }
    }
  }
  
  public static boolean a(String paramString, boolean paramBoolean)
  {
    try
    {
      if (TextUtils.isEmpty(paramString)) {
        return paramBoolean;
      }
      paramString = URLDecoder.decode(paramString).split("/");
      int i = paramString[(paramString.length - 1)].charAt(4);
      return i % 2 == 1;
    }
    catch (Throwable paramString) {}
    return paramBoolean;
  }
  
  /* Error */
  private static a b(Context paramContext, v paramv, String paramString, boolean paramBoolean)
  {
    // Byte code:
    //   0: new 6	com/loc/m$a
    //   3: dup
    //   4: invokespecial 430	com/loc/m$a:<init>	()V
    //   7: astore 15
    //   9: aload 15
    //   11: new 43	org/json/JSONObject
    //   14: dup
    //   15: invokespecial 431	org/json/JSONObject:<init>	()V
    //   18: putfield 297	com/loc/m$a:w	Lorg/json/JSONObject;
    //   21: getstatic 436	com/loc/r$a:a	Lcom/loc/r;
    //   24: aload_0
    //   25: invokevirtual 441	com/loc/r:a	(Landroid/content/Context;)V
    //   28: aconst_null
    //   29: astore 13
    //   31: aconst_null
    //   32: astore 11
    //   34: aconst_null
    //   35: astore 10
    //   37: aconst_null
    //   38: astore 14
    //   40: aload_2
    //   41: astore 6
    //   43: aload_2
    //   44: astore 7
    //   46: aload_2
    //   47: astore 8
    //   49: new 443	com/loc/bj
    //   52: dup
    //   53: invokespecial 444	com/loc/bj:<init>	()V
    //   56: pop
    //   57: aload_2
    //   58: astore 7
    //   60: new 446	java/lang/StringBuilder
    //   63: dup
    //   64: invokespecial 447	java/lang/StringBuilder:<init>	()V
    //   67: astore 6
    //   69: aload_2
    //   70: astore 7
    //   72: aload 6
    //   74: aload_2
    //   75: invokevirtual 451	java/lang/StringBuilder:append	(Ljava/lang/String;)Ljava/lang/StringBuilder;
    //   78: pop
    //   79: aload_2
    //   80: astore 7
    //   82: aload 6
    //   84: ldc_w 453
    //   87: invokevirtual 451	java/lang/StringBuilder:append	(Ljava/lang/String;)Ljava/lang/StringBuilder;
    //   90: pop
    //   91: aload_2
    //   92: astore 7
    //   94: aload 6
    //   96: invokevirtual 454	java/lang/StringBuilder:toString	()Ljava/lang/String;
    //   99: astore 6
    //   101: new 26	com/loc/m$b
    //   104: dup
    //   105: aload_0
    //   106: aload_1
    //   107: aload 6
    //   109: invokespecial 456	com/loc/m$b:<init>	(Landroid/content/Context;Lcom/loc/v;Ljava/lang/String;)V
    //   112: astore_2
    //   113: aload_2
    //   114: aload_2
    //   115: invokevirtual 459	com/loc/m$b:a	()Z
    //   118: invokestatic 462	com/loc/bj:a	(Lcom/loc/bn;Z)Lcom/loc/bo;
    //   121: astore_2
    //   122: aload_2
    //   123: ifnull +56 -> 179
    //   126: aload_2
    //   127: getfield 467	com/loc/bo:a	[B
    //   130: astore 7
    //   132: goto +50 -> 182
    //   135: astore 8
    //   137: aconst_null
    //   138: astore 7
    //   140: aload_2
    //   141: astore 9
    //   143: goto +594 -> 737
    //   146: astore 7
    //   148: aconst_null
    //   149: astore 10
    //   151: aload 11
    //   153: astore 9
    //   155: aload 6
    //   157: astore 8
    //   159: aload 10
    //   161: astore 6
    //   163: goto +616 -> 779
    //   166: astore 7
    //   168: aload 6
    //   170: astore 10
    //   172: aload 7
    //   174: astore 6
    //   176: goto +639 -> 815
    //   179: aconst_null
    //   180: astore 7
    //   182: bipush 16
    //   184: newarray <illegal type>
    //   186: astore 9
    //   188: aload 7
    //   190: arraylength
    //   191: bipush 16
    //   193: isub
    //   194: newarray <illegal type>
    //   196: astore 8
    //   198: aload 7
    //   200: iconst_0
    //   201: aload 9
    //   203: iconst_0
    //   204: bipush 16
    //   206: invokestatic 473	java/lang/System:arraycopy	(Ljava/lang/Object;ILjava/lang/Object;II)V
    //   209: aload 7
    //   211: bipush 16
    //   213: aload 8
    //   215: iconst_0
    //   216: aload 7
    //   218: arraylength
    //   219: bipush 16
    //   221: isub
    //   222: invokestatic 473	java/lang/System:arraycopy	(Ljava/lang/Object;ILjava/lang/Object;II)V
    //   225: new 475	javax/crypto/spec/SecretKeySpec
    //   228: dup
    //   229: aload 9
    //   231: ldc_w 477
    //   234: invokespecial 480	javax/crypto/spec/SecretKeySpec:<init>	([BLjava/lang/String;)V
    //   237: astore 9
    //   239: ldc_w 482
    //   242: invokestatic 488	javax/crypto/Cipher:getInstance	(Ljava/lang/String;)Ljavax/crypto/Cipher;
    //   245: astore 12
    //   247: aload 12
    //   249: iconst_2
    //   250: aload 9
    //   252: new 490	javax/crypto/spec/IvParameterSpec
    //   255: dup
    //   256: invokestatic 493	com/loc/w:c	()[B
    //   259: invokespecial 496	javax/crypto/spec/IvParameterSpec:<init>	([B)V
    //   262: invokevirtual 500	javax/crypto/Cipher:init	(ILjava/security/Key;Ljava/security/spec/AlgorithmParameterSpec;)V
    //   265: aload 12
    //   267: aload 8
    //   269: invokevirtual 504	javax/crypto/Cipher:doFinal	([B)[B
    //   272: invokestatic 507	com/loc/w:a	([B)Ljava/lang/String;
    //   275: astore 8
    //   277: aload 6
    //   279: astore 10
    //   281: aload 7
    //   283: astore 11
    //   285: aload 8
    //   287: astore 12
    //   289: aload_2
    //   290: astore 9
    //   292: aload_0
    //   293: ifnull +580 -> 873
    //   296: aload 7
    //   298: ifnonnull +21 -> 319
    //   301: aload 6
    //   303: astore 10
    //   305: aload 7
    //   307: astore 11
    //   309: aload 8
    //   311: astore 12
    //   313: aload_2
    //   314: astore 9
    //   316: goto +557 -> 873
    //   319: aload_1
    //   320: ifnull +108 -> 428
    //   323: aload_1
    //   324: invokevirtual 88	com/loc/v:a	()Ljava/lang/String;
    //   327: invokestatic 104	android/text/TextUtils:isEmpty	(Ljava/lang/CharSequence;)Z
    //   330: ifeq +6 -> 336
    //   333: goto +95 -> 428
    //   336: new 446	java/lang/StringBuilder
    //   339: dup
    //   340: invokespecial 447	java/lang/StringBuilder:<init>	()V
    //   343: astore 9
    //   345: aload 9
    //   347: aload_0
    //   348: getstatic 510	com/loc/ah:e	Ljava/lang/String;
    //   351: invokestatic 513	com/loc/ah:c	(Landroid/content/Context;Ljava/lang/String;)Ljava/lang/String;
    //   354: invokevirtual 451	java/lang/StringBuilder:append	(Ljava/lang/String;)Ljava/lang/StringBuilder;
    //   357: pop
    //   358: aload 9
    //   360: getstatic 518	java/io/File:separator	Ljava/lang/String;
    //   363: invokevirtual 451	java/lang/StringBuilder:append	(Ljava/lang/String;)Ljava/lang/StringBuilder;
    //   366: pop
    //   367: aload 9
    //   369: aload_1
    //   370: invokevirtual 88	com/loc/v:a	()Ljava/lang/String;
    //   373: invokestatic 522	com/loc/s:b	(Ljava/lang/String;)Ljava/lang/String;
    //   376: invokevirtual 451	java/lang/StringBuilder:append	(Ljava/lang/String;)Ljava/lang/StringBuilder;
    //   379: pop
    //   380: aload 9
    //   382: invokevirtual 454	java/lang/StringBuilder:toString	()Ljava/lang/String;
    //   385: astore 10
    //   387: goto +44 -> 431
    //   390: astore 9
    //   392: aload 7
    //   394: astore 10
    //   396: aload 9
    //   398: astore 7
    //   400: aload 8
    //   402: astore 9
    //   404: aload 6
    //   406: astore 8
    //   408: aload 10
    //   410: astore 6
    //   412: goto +367 -> 779
    //   415: astore 9
    //   417: aload 6
    //   419: astore 10
    //   421: aload 8
    //   423: astore 6
    //   425: goto +408 -> 833
    //   428: aconst_null
    //   429: astore 10
    //   431: aload 14
    //   433: astore 9
    //   435: new 515	java/io/File
    //   438: dup
    //   439: aload 10
    //   441: invokespecial 524	java/io/File:<init>	(Ljava/lang/String;)V
    //   444: astore 10
    //   446: aload 14
    //   448: astore 9
    //   450: aload 10
    //   452: invokevirtual 528	java/io/File:getParentFile	()Ljava/io/File;
    //   455: invokevirtual 531	java/io/File:exists	()Z
    //   458: ifne +16 -> 474
    //   461: aload 14
    //   463: astore 9
    //   465: aload 10
    //   467: invokevirtual 528	java/io/File:getParentFile	()Ljava/io/File;
    //   470: invokevirtual 534	java/io/File:mkdirs	()Z
    //   473: pop
    //   474: aload 14
    //   476: astore 9
    //   478: new 536	java/io/FileOutputStream
    //   481: dup
    //   482: aload 10
    //   484: iconst_0
    //   485: invokespecial 539	java/io/FileOutputStream:<init>	(Ljava/io/File;Z)V
    //   488: astore 10
    //   490: aload 10
    //   492: aload 7
    //   494: invokevirtual 542	java/io/FileOutputStream:write	([B)V
    //   497: aload 10
    //   499: invokevirtual 545	java/io/FileOutputStream:close	()V
    //   502: aload 6
    //   504: astore 10
    //   506: aload 7
    //   508: astore 11
    //   510: aload 8
    //   512: astore 12
    //   514: aload_2
    //   515: astore 9
    //   517: goto +356 -> 873
    //   520: astore 9
    //   522: goto +89 -> 611
    //   525: astore 9
    //   527: aload 10
    //   529: astore 13
    //   531: aload 9
    //   533: astore 10
    //   535: goto +18 -> 553
    //   538: astore 11
    //   540: aload 9
    //   542: astore 10
    //   544: aload 11
    //   546: astore 9
    //   548: goto +63 -> 611
    //   551: astore 10
    //   553: aload 13
    //   555: astore 9
    //   557: aload 10
    //   559: ldc_w 547
    //   562: ldc_w 547
    //   565: invokestatic 277	com/loc/aj:b	(Ljava/lang/Throwable;Ljava/lang/String;Ljava/lang/String;)V
    //   568: aload 6
    //   570: astore 10
    //   572: aload 7
    //   574: astore 11
    //   576: aload 8
    //   578: astore 12
    //   580: aload_2
    //   581: astore 9
    //   583: aload 13
    //   585: ifnull +288 -> 873
    //   588: aload 13
    //   590: invokevirtual 545	java/io/FileOutputStream:close	()V
    //   593: aload 6
    //   595: astore 10
    //   597: aload 7
    //   599: astore 11
    //   601: aload 8
    //   603: astore 12
    //   605: aload_2
    //   606: astore 9
    //   608: goto +265 -> 873
    //   611: aload 10
    //   613: ifnull +8 -> 621
    //   616: aload 10
    //   618: invokevirtual 545	java/io/FileOutputStream:close	()V
    //   621: aload 9
    //   623: athrow
    //   624: astore 8
    //   626: aload_2
    //   627: astore 9
    //   629: goto +108 -> 737
    //   632: astore 8
    //   634: aload 7
    //   636: astore 10
    //   638: aload 8
    //   640: astore 7
    //   642: aload 11
    //   644: astore 9
    //   646: aload 6
    //   648: astore 8
    //   650: aload 10
    //   652: astore 6
    //   654: goto +125 -> 779
    //   657: astore 9
    //   659: aconst_null
    //   660: astore 8
    //   662: aload 6
    //   664: astore 10
    //   666: aload 8
    //   668: astore 6
    //   670: goto +163 -> 833
    //   673: astore 7
    //   675: aload 6
    //   677: astore 8
    //   679: goto +90 -> 769
    //   682: aload 6
    //   684: astore_2
    //   685: goto +11 -> 696
    //   688: astore 9
    //   690: aload 6
    //   692: astore_2
    //   693: goto +23 -> 716
    //   696: aload_2
    //   697: astore 6
    //   699: aload_2
    //   700: astore 7
    //   702: aload_2
    //   703: astore 8
    //   705: new 66	com/loc/k
    //   708: dup
    //   709: ldc_w 549
    //   712: invokespecial 550	com/loc/k:<init>	(Ljava/lang/String;)V
    //   715: athrow
    //   716: aload_2
    //   717: astore 6
    //   719: aload_2
    //   720: astore 7
    //   722: aload_2
    //   723: astore 8
    //   725: aload 9
    //   727: athrow
    //   728: astore 8
    //   730: aconst_null
    //   731: astore 9
    //   733: aload 9
    //   735: astore 7
    //   737: aload 8
    //   739: ldc_w 270
    //   742: ldc_w 552
    //   745: invokestatic 277	com/loc/aj:b	(Ljava/lang/Throwable;Ljava/lang/String;Ljava/lang/String;)V
    //   748: aload_0
    //   749: aload_1
    //   750: aload 8
    //   752: invokestatic 554	com/loc/m:a	(Landroid/content/Context;Lcom/loc/v;Ljava/lang/Throwable;)V
    //   755: aload 10
    //   757: astore_2
    //   758: goto +126 -> 884
    //   761: astore_2
    //   762: aload 7
    //   764: astore 8
    //   766: aload_2
    //   767: astore 7
    //   769: aconst_null
    //   770: astore 6
    //   772: aload 6
    //   774: astore_2
    //   775: aload 11
    //   777: astore 9
    //   779: aload_0
    //   780: aload_1
    //   781: aload 7
    //   783: invokestatic 554	com/loc/m:a	(Landroid/content/Context;Lcom/loc/v;Ljava/lang/Throwable;)V
    //   786: aload 6
    //   788: astore 7
    //   790: aload_2
    //   791: astore 10
    //   793: aload 9
    //   795: astore_2
    //   796: aload 8
    //   798: astore 6
    //   800: aload 10
    //   802: astore 9
    //   804: goto +80 -> 884
    //   807: astore 6
    //   809: aconst_null
    //   810: astore_2
    //   811: aload 8
    //   813: astore 10
    //   815: aconst_null
    //   816: astore 7
    //   818: aload 6
    //   820: astore 9
    //   822: aconst_null
    //   823: astore 8
    //   825: aload 7
    //   827: astore 6
    //   829: aload 8
    //   831: astore 7
    //   833: aload 15
    //   835: aload 9
    //   837: invokevirtual 555	com/loc/k:a	()Ljava/lang/String;
    //   840: putfield 556	com/loc/m$a:a	Ljava/lang/String;
    //   843: aload_0
    //   844: aload_1
    //   845: aload 9
    //   847: invokevirtual 555	com/loc/k:a	()Ljava/lang/String;
    //   850: invokestatic 131	com/loc/m:a	(Landroid/content/Context;Lcom/loc/v;Ljava/lang/String;)V
    //   853: aload_1
    //   854: ldc_w 558
    //   857: aload 9
    //   859: invokestatic 561	com/loc/aj:a	(Lcom/loc/v;Ljava/lang/String;Lcom/loc/k;)V
    //   862: aload_2
    //   863: astore 9
    //   865: aload 6
    //   867: astore 12
    //   869: aload 7
    //   871: astore 11
    //   873: aload 12
    //   875: astore_2
    //   876: aload 11
    //   878: astore 7
    //   880: aload 10
    //   882: astore 6
    //   884: aload 7
    //   886: ifnonnull +6 -> 892
    //   889: aload 15
    //   891: areturn
    //   892: aload_2
    //   893: astore 8
    //   895: aload_2
    //   896: invokestatic 104	android/text/TextUtils:isEmpty	(Ljava/lang/CharSequence;)Z
    //   899: ifeq +10 -> 909
    //   902: aload 7
    //   904: invokestatic 507	com/loc/w:a	([B)Ljava/lang/String;
    //   907: astore 8
    //   909: aload 8
    //   911: invokestatic 104	android/text/TextUtils:isEmpty	(Ljava/lang/CharSequence;)Z
    //   914: ifeq +11 -> 925
    //   917: aload_0
    //   918: aload_1
    //   919: ldc_w 563
    //   922: invokestatic 131	com/loc/m:a	(Landroid/content/Context;Lcom/loc/v;Ljava/lang/String;)V
    //   925: new 43	org/json/JSONObject
    //   928: dup
    //   929: aload 8
    //   931: invokespecial 564	org/json/JSONObject:<init>	(Ljava/lang/String;)V
    //   934: astore 10
    //   936: aload 10
    //   938: ldc_w 566
    //   941: invokevirtual 47	org/json/JSONObject:has	(Ljava/lang/String;)Z
    //   944: ifeq +478 -> 1422
    //   947: aload 10
    //   949: ldc_w 566
    //   952: invokevirtual 570	org/json/JSONObject:getInt	(Ljava/lang/String;)I
    //   955: istore 4
    //   957: iload 4
    //   959: iconst_1
    //   960: if_icmpne +10 -> 970
    //   963: iconst_1
    //   964: putstatic 572	com/loc/m:a	I
    //   967: goto +127 -> 1094
    //   970: iload 4
    //   972: ifne +122 -> 1094
    //   975: ldc_w 574
    //   978: astore_2
    //   979: ldc_w 576
    //   982: astore 7
    //   984: aload 9
    //   986: ifnull +16 -> 1002
    //   989: aload 9
    //   991: getfield 577	com/loc/bo:c	Ljava/lang/String;
    //   994: astore_2
    //   995: aload 9
    //   997: getfield 578	com/loc/bo:d	Ljava/lang/String;
    //   1000: astore 7
    //   1002: aload_0
    //   1003: aload_2
    //   1004: aload 7
    //   1006: aload 10
    //   1008: invokestatic 581	com/loc/w:a	(Landroid/content/Context;Ljava/lang/String;Ljava/lang/String;Lorg/json/JSONObject;)V
    //   1011: iconst_0
    //   1012: putstatic 572	com/loc/m:a	I
    //   1015: aload 10
    //   1017: ldc_w 583
    //   1020: invokevirtual 47	org/json/JSONObject:has	(Ljava/lang/String;)Z
    //   1023: ifeq +14 -> 1037
    //   1026: aload 10
    //   1028: ldc_w 583
    //   1031: invokevirtual 51	org/json/JSONObject:getString	(Ljava/lang/String;)Ljava/lang/String;
    //   1034: putstatic 584	com/loc/m:b	Ljava/lang/String;
    //   1037: ldc 31
    //   1039: astore 8
    //   1041: aload 10
    //   1043: ldc_w 586
    //   1046: invokevirtual 47	org/json/JSONObject:has	(Ljava/lang/String;)Z
    //   1049: ifeq +13 -> 1062
    //   1052: aload 10
    //   1054: ldc_w 586
    //   1057: invokevirtual 51	org/json/JSONObject:getString	(Ljava/lang/String;)Ljava/lang/String;
    //   1060: astore 8
    //   1062: aload_1
    //   1063: ldc_w 558
    //   1066: getstatic 584	com/loc/m:b	Ljava/lang/String;
    //   1069: aload 7
    //   1071: aload_2
    //   1072: aload 8
    //   1074: invokestatic 589	com/loc/aj:a	(Lcom/loc/v;Ljava/lang/String;Ljava/lang/String;Ljava/lang/String;Ljava/lang/String;Ljava/lang/String;)V
    //   1077: getstatic 572	com/loc/m:a	I
    //   1080: ifne +14 -> 1094
    //   1083: aload 15
    //   1085: getstatic 584	com/loc/m:b	Ljava/lang/String;
    //   1088: putfield 556	com/loc/m$a:a	Ljava/lang/String;
    //   1091: aload 15
    //   1093: areturn
    //   1094: aload 10
    //   1096: ldc_w 591
    //   1099: invokevirtual 47	org/json/JSONObject:has	(Ljava/lang/String;)Z
    //   1102: ifeq +30 -> 1132
    //   1105: aload 15
    //   1107: aload 10
    //   1109: ldc_w 591
    //   1112: invokevirtual 570	org/json/JSONObject:getInt	(Ljava/lang/String;)I
    //   1115: putfield 593	com/loc/m$a:b	I
    //   1118: goto +14 -> 1132
    //   1121: astore_1
    //   1122: aload_1
    //   1123: ldc_w 270
    //   1126: ldc_w 552
    //   1129: invokestatic 311	com/loc/ag:a	(Ljava/lang/Throwable;Ljava/lang/String;Ljava/lang/String;)V
    //   1132: aload 10
    //   1134: ldc_w 595
    //   1137: invokestatic 144	com/loc/w:a	(Lorg/json/JSONObject;Ljava/lang/String;)Z
    //   1140: ifeq +282 -> 1422
    //   1143: aload 10
    //   1145: ldc_w 595
    //   1148: invokevirtual 148	org/json/JSONObject:getJSONObject	(Ljava/lang/String;)Lorg/json/JSONObject;
    //   1151: astore_1
    //   1152: aload 6
    //   1154: aload 15
    //   1156: aload_1
    //   1157: invokestatic 597	com/loc/m:a	(Ljava/lang/String;Lcom/loc/m$a;Lorg/json/JSONObject;)V
    //   1160: aload_1
    //   1161: ldc_w 599
    //   1164: invokestatic 144	com/loc/w:a	(Lorg/json/JSONObject;Ljava/lang/String;)Z
    //   1167: ifeq +137 -> 1304
    //   1170: aload_0
    //   1171: invokestatic 604	com/loc/p:b	(Landroid/content/Context;)Ljava/lang/String;
    //   1174: invokestatic 104	android/text/TextUtils:isEmpty	(Ljava/lang/CharSequence;)Z
    //   1177: ifeq +127 -> 1304
    //   1180: aload_1
    //   1181: ldc_w 599
    //   1184: invokevirtual 148	org/json/JSONObject:getJSONObject	(Ljava/lang/String;)Lorg/json/JSONObject;
    //   1187: astore 6
    //   1189: new 11	com/loc/m$a$b
    //   1192: dup
    //   1193: invokespecial 205	com/loc/m$a$b:<init>	()V
    //   1196: astore_2
    //   1197: aload_2
    //   1198: aload 6
    //   1200: ldc_w 315
    //   1203: invokevirtual 62	org/json/JSONObject:optString	(Ljava/lang/String;)Ljava/lang/String;
    //   1206: iconst_0
    //   1207: invokestatic 318	com/loc/m:a	(Ljava/lang/String;Z)Z
    //   1210: putfield 410	com/loc/m$a$b:a	Z
    //   1213: aload_2
    //   1214: aload 6
    //   1216: ldc_w 339
    //   1219: invokevirtual 62	org/json/JSONObject:optString	(Ljava/lang/String;)Ljava/lang/String;
    //   1222: putfield 408	com/loc/m$a$b:b	Ljava/lang/String;
    //   1225: aload_2
    //   1226: aload 6
    //   1228: ldc_w 335
    //   1231: invokevirtual 62	org/json/JSONObject:optString	(Ljava/lang/String;)Ljava/lang/String;
    //   1234: putfield 407	com/loc/m$a$b:c	Ljava/lang/String;
    //   1237: aload_2
    //   1238: getfield 410	com/loc/m$a$b:a	Z
    //   1241: ifeq +56 -> 1297
    //   1244: invokestatic 609	com/loc/x:a	()Lcom/loc/v;
    //   1247: astore 6
    //   1249: aload 6
    //   1251: ifnull +53 -> 1304
    //   1254: new 611	com/loc/au
    //   1257: dup
    //   1258: aload_2
    //   1259: getfield 408	com/loc/m$a$b:b	Ljava/lang/String;
    //   1262: aload_2
    //   1263: getfield 407	com/loc/m$a$b:c	Ljava/lang/String;
    //   1266: aload 15
    //   1268: invokestatic 614	com/loc/m$a:a	(Lcom/loc/m$a;)Z
    //   1271: invokespecial 617	com/loc/au:<init>	(Ljava/lang/String;Ljava/lang/String;Z)V
    //   1274: astore_2
    //   1275: aload_2
    //   1276: iload_3
    //   1277: invokevirtual 620	com/loc/au:a	(Z)V
    //   1280: new 622	com/loc/at
    //   1283: dup
    //   1284: aload_0
    //   1285: aload_2
    //   1286: aload 6
    //   1288: invokespecial 625	com/loc/at:<init>	(Landroid/content/Context;Lcom/loc/au;Lcom/loc/v;)V
    //   1291: invokevirtual 627	com/loc/at:a	()V
    //   1294: goto +10 -> 1304
    //   1297: aload_0
    //   1298: ldc_w 629
    //   1301: invokestatic 632	com/loc/az:a	(Landroid/content/Context;Ljava/lang/String;)V
    //   1304: aload_1
    //   1305: ldc_w 634
    //   1308: invokestatic 144	com/loc/w:a	(Lorg/json/JSONObject;Ljava/lang/String;)Z
    //   1311: ifeq +45 -> 1356
    //   1314: aload_1
    //   1315: ldc_w 634
    //   1318: invokevirtual 148	org/json/JSONObject:getJSONObject	(Ljava/lang/String;)Lorg/json/JSONObject;
    //   1321: astore_2
    //   1322: aload_2
    //   1323: ldc_w 636
    //   1326: invokevirtual 62	org/json/JSONObject:optString	(Ljava/lang/String;)Ljava/lang/String;
    //   1329: iconst_0
    //   1330: invokestatic 318	com/loc/m:a	(Ljava/lang/String;Z)Z
    //   1333: istore_3
    //   1334: aload_2
    //   1335: ldc_w 638
    //   1338: invokevirtual 62	org/json/JSONObject:optString	(Ljava/lang/String;)Ljava/lang/String;
    //   1341: iconst_0
    //   1342: invokestatic 318	com/loc/m:a	(Ljava/lang/String;Z)Z
    //   1345: istore 5
    //   1347: iload_3
    //   1348: putstatic 639	com/loc/x:e	Z
    //   1351: iload 5
    //   1353: putstatic 641	com/loc/x:f	Z
    //   1356: aload_1
    //   1357: ldc_w 643
    //   1360: invokevirtual 148	org/json/JSONObject:getJSONObject	(Ljava/lang/String;)Lorg/json/JSONObject;
    //   1363: astore_1
    //   1364: aload_1
    //   1365: ldc_w 645
    //   1368: invokevirtual 62	org/json/JSONObject:optString	(Ljava/lang/String;)Ljava/lang/String;
    //   1371: iconst_0
    //   1372: invokestatic 318	com/loc/m:a	(Ljava/lang/String;Z)Z
    //   1375: istore_3
    //   1376: aload_1
    //   1377: ldc_w 315
    //   1380: invokevirtual 62	org/json/JSONObject:optString	(Ljava/lang/String;)Ljava/lang/String;
    //   1383: iconst_0
    //   1384: invokestatic 318	com/loc/m:a	(Ljava/lang/String;Z)Z
    //   1387: ifne +13 -> 1400
    //   1390: getstatic 436	com/loc/r$a:a	Lcom/loc/r;
    //   1393: aload_0
    //   1394: invokevirtual 647	com/loc/r:b	(Landroid/content/Context;)V
    //   1397: aload 15
    //   1399: areturn
    //   1400: getstatic 436	com/loc/r$a:a	Lcom/loc/r;
    //   1403: aload_0
    //   1404: iload_3
    //   1405: invokevirtual 650	com/loc/r:a	(Landroid/content/Context;Z)V
    //   1408: aload 15
    //   1410: areturn
    //   1411: astore_0
    //   1412: aload_0
    //   1413: ldc_w 270
    //   1416: ldc_w 552
    //   1419: invokestatic 311	com/loc/ag:a	(Ljava/lang/Throwable;Ljava/lang/String;Ljava/lang/String;)V
    //   1422: aload 15
    //   1424: areturn
    //   1425: astore 6
    //   1427: goto -731 -> 696
    //   1430: astore_2
    //   1431: goto -749 -> 682
    //   1434: astore 9
    //   1436: aload 6
    //   1438: astore 10
    //   1440: aload 7
    //   1442: astore 11
    //   1444: aload 8
    //   1446: astore 12
    //   1448: aload_2
    //   1449: astore 9
    //   1451: goto -578 -> 873
    //   1454: astore 10
    //   1456: goto -835 -> 621
    //   1459: astore_0
    //   1460: aload 15
    //   1462: areturn
    //   1463: astore 9
    //   1465: goto -749 -> 716
    // Local variable table:
    //   start	length	slot	name	signature
    //   0	1468	0	paramContext	Context
    //   0	1468	1	paramv	v
    //   0	1468	2	paramString	String
    //   0	1468	3	paramBoolean	boolean
    //   955	16	4	i	int
    //   1345	7	5	bool	boolean
    //   41	758	6	localObject1	Object
    //   807	12	6	localk1	k
    //   827	460	6	localObject2	Object
    //   1425	12	6	localThrowable1	Throwable
    //   44	95	7	localObject3	Object
    //   146	1	7	localIllegalBlockSizeException1	javax.crypto.IllegalBlockSizeException
    //   166	7	7	localk2	k
    //   180	461	7	localObject4	Object
    //   673	1	7	localIllegalBlockSizeException2	javax.crypto.IllegalBlockSizeException
    //   700	741	7	localObject5	Object
    //   47	1	8	str1	String
    //   135	1	8	localThrowable2	Throwable
    //   157	445	8	localObject6	Object
    //   624	1	8	localThrowable3	Throwable
    //   632	7	8	localIllegalBlockSizeException3	javax.crypto.IllegalBlockSizeException
    //   648	76	8	localObject7	Object
    //   728	23	8	localThrowable4	Throwable
    //   764	681	8	localObject8	Object
    //   141	240	9	localObject9	Object
    //   390	7	9	localIllegalBlockSizeException4	javax.crypto.IllegalBlockSizeException
    //   402	1	9	localObject10	Object
    //   415	1	9	localk3	k
    //   433	83	9	localObject11	Object
    //   520	1	9	localObject12	Object
    //   525	16	9	localThrowable5	Throwable
    //   546	99	9	localObject13	Object
    //   657	1	9	localk4	k
    //   688	38	9	localk5	k
    //   731	265	9	localObject14	Object
    //   1434	1	9	localThrowable6	Throwable
    //   1449	1	9	str2	String
    //   1463	1	9	localk6	k
    //   35	508	10	localObject15	Object
    //   551	7	10	localThrowable7	Throwable
    //   570	869	10	localObject16	Object
    //   1454	1	10	localThrowable8	Throwable
    //   32	477	11	localObject17	Object
    //   538	7	11	localObject18	Object
    //   574	869	11	localObject19	Object
    //   245	1202	12	localObject20	Object
    //   29	560	13	localObject21	Object
    //   38	437	14	localObject22	Object
    //   7	1454	15	locala	a
    // Exception table:
    //   from	to	target	type
    //   126	132	135	java/lang/Throwable
    //   126	132	146	javax/crypto/IllegalBlockSizeException
    //   126	132	166	com/loc/k
    //   323	333	390	javax/crypto/IllegalBlockSizeException
    //   336	387	390	javax/crypto/IllegalBlockSizeException
    //   497	502	390	javax/crypto/IllegalBlockSizeException
    //   588	593	390	javax/crypto/IllegalBlockSizeException
    //   616	621	390	javax/crypto/IllegalBlockSizeException
    //   621	624	390	javax/crypto/IllegalBlockSizeException
    //   323	333	415	com/loc/k
    //   336	387	415	com/loc/k
    //   497	502	415	com/loc/k
    //   588	593	415	com/loc/k
    //   616	621	415	com/loc/k
    //   621	624	415	com/loc/k
    //   490	497	520	finally
    //   490	497	525	java/lang/Throwable
    //   435	446	538	finally
    //   450	461	538	finally
    //   465	474	538	finally
    //   478	490	538	finally
    //   557	568	538	finally
    //   435	446	551	java/lang/Throwable
    //   450	461	551	java/lang/Throwable
    //   465	474	551	java/lang/Throwable
    //   478	490	551	java/lang/Throwable
    //   182	277	624	java/lang/Throwable
    //   182	277	632	javax/crypto/IllegalBlockSizeException
    //   182	277	657	com/loc/k
    //   101	122	673	javax/crypto/IllegalBlockSizeException
    //   101	122	688	com/loc/k
    //   49	57	728	java/lang/Throwable
    //   705	716	728	java/lang/Throwable
    //   725	728	728	java/lang/Throwable
    //   49	57	761	javax/crypto/IllegalBlockSizeException
    //   60	69	761	javax/crypto/IllegalBlockSizeException
    //   72	79	761	javax/crypto/IllegalBlockSizeException
    //   82	91	761	javax/crypto/IllegalBlockSizeException
    //   94	101	761	javax/crypto/IllegalBlockSizeException
    //   705	716	761	javax/crypto/IllegalBlockSizeException
    //   725	728	761	javax/crypto/IllegalBlockSizeException
    //   49	57	807	com/loc/k
    //   705	716	807	com/loc/k
    //   725	728	807	com/loc/k
    //   1094	1118	1121	java/lang/Throwable
    //   925	957	1411	java/lang/Throwable
    //   963	967	1411	java/lang/Throwable
    //   989	1002	1411	java/lang/Throwable
    //   1002	1037	1411	java/lang/Throwable
    //   1041	1062	1411	java/lang/Throwable
    //   1062	1091	1411	java/lang/Throwable
    //   1122	1132	1411	java/lang/Throwable
    //   1132	1249	1411	java/lang/Throwable
    //   1254	1294	1411	java/lang/Throwable
    //   1297	1304	1411	java/lang/Throwable
    //   1304	1356	1411	java/lang/Throwable
    //   60	69	1425	java/lang/Throwable
    //   72	79	1425	java/lang/Throwable
    //   82	91	1425	java/lang/Throwable
    //   94	101	1425	java/lang/Throwable
    //   101	122	1430	java/lang/Throwable
    //   323	333	1434	java/lang/Throwable
    //   336	387	1434	java/lang/Throwable
    //   497	502	1434	java/lang/Throwable
    //   588	593	1434	java/lang/Throwable
    //   621	624	1434	java/lang/Throwable
    //   616	621	1454	java/lang/Throwable
    //   1356	1397	1459	java/lang/Throwable
    //   1400	1408	1459	java/lang/Throwable
    //   60	69	1463	com/loc/k
    //   72	79	1463	com/loc/k
    //   82	91	1463	com/loc/k
    //   94	101	1463	com/loc/k
  }
  
  public static final class a
  {
    @Deprecated
    public c A;
    public c B;
    public b C;
    public b D;
    public b E;
    public b F;
    public e G;
    private boolean H;
    public String a;
    public int b = -1;
    @Deprecated
    public JSONObject c;
    @Deprecated
    public JSONObject d;
    @Deprecated
    public JSONObject e;
    @Deprecated
    public JSONObject f;
    @Deprecated
    public JSONObject g;
    @Deprecated
    public JSONObject h;
    @Deprecated
    public JSONObject i;
    @Deprecated
    public JSONObject j;
    @Deprecated
    public JSONObject k;
    @Deprecated
    public JSONObject l;
    @Deprecated
    public JSONObject m;
    @Deprecated
    public JSONObject n;
    @Deprecated
    public JSONObject o;
    @Deprecated
    public JSONObject p;
    @Deprecated
    public JSONObject q;
    @Deprecated
    public JSONObject r;
    @Deprecated
    public JSONObject s;
    @Deprecated
    public JSONObject t;
    @Deprecated
    public JSONObject u;
    @Deprecated
    public JSONObject v;
    public JSONObject w;
    public a x;
    public d y;
    public f z;
    
    public final boolean a()
    {
      return this.H;
    }
    
    public static final class a
    {
      public boolean a;
      public boolean b;
      public JSONObject c;
    }
    
    public static final class b
    {
      public boolean a;
      public String b;
      public String c;
      public String d;
      public boolean e;
    }
    
    public static final class c
    {
      public String a;
      public String b;
    }
    
    public static final class d
    {
      public String a;
      public String b;
      public String c;
    }
    
    public static final class e
    {
      public boolean a;
      public boolean b;
      public boolean c;
      public String d;
      public String e;
      public String f;
    }
    
    public static final class f
    {
      public boolean a;
    }
  }
  
  static final class b
    extends bk
  {
    private String f;
    private Map<String, String> g;
    private boolean h;
    
    b(Context paramContext, v paramv, String paramString)
    {
      super(paramv);
      this.f = paramString;
      this.g = null;
      boolean bool;
      if (Build.VERSION.SDK_INT != 19) {
        bool = true;
      } else {
        bool = false;
      }
      this.h = bool;
    }
    
    public final boolean a()
    {
      return this.h;
    }
    
    public final byte[] a_()
    {
      return null;
    }
    
    public final Map<String, String> b()
    {
      return null;
    }
    
    public final String c()
    {
      if (this.h) {
        return "https://restapi.amap.com/v3/iasdkauth";
      }
      return "http://restapi.amap.com/v3/iasdkauth";
    }
    
    public final byte[] e()
    {
      Object localObject2 = p.w(this.a);
      Object localObject1 = localObject2;
      if (TextUtils.isEmpty((CharSequence)localObject2)) {
        localObject1 = p.j(this.a);
      }
      localObject2 = localObject1;
      if (!TextUtils.isEmpty((CharSequence)localObject1)) {
        localObject2 = s.b(new StringBuilder((String)localObject1).reverse().toString());
      }
      localObject1 = new HashMap();
      ((Map)localObject1).put("authkey", this.f);
      ((Map)localObject1).put("plattype", "android");
      ((Map)localObject1).put("product", this.b.a());
      ((Map)localObject1).put("version", this.b.b());
      ((Map)localObject1).put("output", "json");
      StringBuilder localStringBuilder = new StringBuilder();
      localStringBuilder.append(Build.VERSION.SDK_INT);
      ((Map)localObject1).put("androidversion", localStringBuilder.toString());
      ((Map)localObject1).put("deviceId", localObject2);
      ((Map)localObject1).put("manufacture", Build.MANUFACTURER);
      if ((this.g != null) && (!this.g.isEmpty())) {
        ((Map)localObject1).putAll(this.g);
      }
      ((Map)localObject1).put("abitype", w.a(this.a));
      ((Map)localObject1).put("ext", this.b.d());
      return w.a(w.a((Map)localObject1));
    }
    
    protected final String f()
    {
      return "3.0";
    }
  }
}


/* Location:              C:\Users\lixia\Desktop\android反编译三件套\dex2jar-2.0\classes-dex2jar.jar!\com\loc\m.class
 * Java compiler version: 6 (50.0)
 * JD-Core Version:       0.7.1
 */