package com.amap.api.mapcore.util;

import android.content.Context;
import android.text.TextUtils;
import java.io.File;
import java.security.PublicKey;
import java.security.cert.Certificate;
import java.util.Date;
import java.util.concurrent.ExecutorService;

class hh
  extends hf
{
  private PublicKey i = null;
  
  hh(Context paramContext, fv paramfv, boolean paramBoolean)
    throws Exception
  {
    super(paramContext, paramfv, paramBoolean);
    paramfv = gw.b(paramContext, paramfv.a(), paramfv.b());
    String str = gw.a(paramContext);
    b(paramfv, str);
    File localFile = new File(paramfv);
    if (!hb.b().a(this.e).b)
    {
      if (paramBoolean)
      {
        StringBuilder localStringBuilder = new StringBuilder();
        localStringBuilder.append(str);
        localStringBuilder.append(File.separator);
        localStringBuilder.append(gw.a(localFile.getName()));
        a(paramfv, localStringBuilder.toString());
        b(paramContext, paramfv, str);
      }
      return;
    }
    throw new Exception("file is downloading");
  }
  
  private void a(go paramgo, File paramFile)
  {
    paramgo = gw.a.a(paramgo, paramFile.getName());
    if (paramgo != null) {
      this.f = paramgo.e();
    }
  }
  
  /* Error */
  private void a(java.util.jar.JarFile paramJarFile, java.util.jar.JarEntry paramJarEntry)
    throws java.io.IOException
  {
    // Byte code:
    //   0: aconst_null
    //   1: astore 5
    //   3: aconst_null
    //   4: astore 4
    //   6: aload_1
    //   7: aload_2
    //   8: invokevirtual 114	java/util/jar/JarFile:getInputStream	(Ljava/util/zip/ZipEntry;)Ljava/io/InputStream;
    //   11: astore_1
    //   12: sipush 8192
    //   15: newarray <illegal type>
    //   17: astore_2
    //   18: aload_1
    //   19: aload_2
    //   20: invokevirtual 120	java/io/InputStream:read	([B)I
    //   23: istore_3
    //   24: iload_3
    //   25: ifle +6 -> 31
    //   28: goto -10 -> 18
    //   31: aload_1
    //   32: invokestatic 125	com/amap/api/mapcore/util/hd:a	(Ljava/io/Closeable;)V
    //   35: return
    //   36: astore_2
    //   37: aload_1
    //   38: astore 4
    //   40: aload_2
    //   41: astore_1
    //   42: goto +37 -> 79
    //   45: astore_2
    //   46: goto +11 -> 57
    //   49: astore_1
    //   50: goto +29 -> 79
    //   53: astore_2
    //   54: aload 5
    //   56: astore_1
    //   57: aload_1
    //   58: astore 4
    //   60: aload_2
    //   61: ldc 127
    //   63: ldc -127
    //   65: invokestatic 132	com/amap/api/mapcore/util/hd:a	(Ljava/lang/Throwable;Ljava/lang/String;Ljava/lang/String;)V
    //   68: aload_1
    //   69: invokestatic 125	com/amap/api/mapcore/util/hd:a	(Ljava/io/Closeable;)V
    //   72: return
    //   73: astore_1
    //   74: aload_1
    //   75: invokevirtual 135	java/lang/Throwable:printStackTrace	()V
    //   78: return
    //   79: aload 4
    //   81: invokestatic 125	com/amap/api/mapcore/util/hd:a	(Ljava/io/Closeable;)V
    //   84: goto +8 -> 92
    //   87: astore_2
    //   88: aload_2
    //   89: invokevirtual 135	java/lang/Throwable:printStackTrace	()V
    //   92: aload_1
    //   93: athrow
    // Local variable table:
    //   start	length	slot	name	signature
    //   0	94	0	this	hh
    //   0	94	1	paramJarFile	java.util.jar.JarFile
    //   0	94	2	paramJarEntry	java.util.jar.JarEntry
    //   23	2	3	j	int
    //   4	76	4	localJarFile	java.util.jar.JarFile
    //   1	54	5	localObject	Object
    // Exception table:
    //   from	to	target	type
    //   12	18	36	finally
    //   18	24	36	finally
    //   12	18	45	java/lang/Throwable
    //   18	24	45	java/lang/Throwable
    //   6	12	49	finally
    //   60	68	49	finally
    //   6	12	53	java/lang/Throwable
    //   31	35	73	java/lang/Throwable
    //   68	72	73	java/lang/Throwable
    //   79	84	87	java/lang/Throwable
  }
  
  private boolean a(go paramgo, fv paramfv, String paramString)
  {
    if (a(new File(paramString))) {
      return hd.a(paramgo, gw.a(this.a, paramfv.a(), paramfv.b()), paramString, paramfv);
    }
    return false;
  }
  
  private boolean a(go paramgo, String paramString1, String paramString2)
  {
    String str = gw.a(this.a, paramString1);
    if (hd.a(paramgo, paramString1, str, this.e)) {
      return true;
    }
    if (gw.a.a(paramgo, paramString1) != null) {
      return false;
    }
    if (!TextUtils.isEmpty(this.f)) {
      gw.a.a(paramgo, new gz.a(paramString1, fs.a(str), this.e.a(), this.e.b(), paramString2).a("useod").a(), gz.b(paramString1));
    }
    return true;
  }
  
  /* Error */
  private boolean a(File paramFile)
  {
    // Byte code:
    //   0: aconst_null
    //   1: astore 5
    //   3: aconst_null
    //   4: astore 4
    //   6: aload 4
    //   8: astore_3
    //   9: aload_0
    //   10: invokespecial 181	com/amap/api/mapcore/util/hh:c	()V
    //   13: aload 4
    //   15: astore_3
    //   16: new 110	java/util/jar/JarFile
    //   19: dup
    //   20: aload_1
    //   21: invokespecial 184	java/util/jar/JarFile:<init>	(Ljava/io/File;)V
    //   24: astore 4
    //   26: aload 4
    //   28: ldc -70
    //   30: invokevirtual 190	java/util/jar/JarFile:getJarEntry	(Ljava/lang/String;)Ljava/util/jar/JarEntry;
    //   33: astore_3
    //   34: aload_3
    //   35: ifnonnull +10 -> 45
    //   38: aload 4
    //   40: invokevirtual 193	java/util/jar/JarFile:close	()V
    //   43: iconst_0
    //   44: ireturn
    //   45: aload_0
    //   46: aload 4
    //   48: aload_3
    //   49: invokespecial 195	com/amap/api/mapcore/util/hh:a	(Ljava/util/jar/JarFile;Ljava/util/jar/JarEntry;)V
    //   52: aload_3
    //   53: invokevirtual 201	java/util/jar/JarEntry:getCertificates	()[Ljava/security/cert/Certificate;
    //   56: astore_3
    //   57: aload_3
    //   58: ifnonnull +10 -> 68
    //   61: aload 4
    //   63: invokevirtual 193	java/util/jar/JarFile:close	()V
    //   66: iconst_0
    //   67: ireturn
    //   68: aload_0
    //   69: aload_1
    //   70: aload_3
    //   71: invokespecial 204	com/amap/api/mapcore/util/hh:a	(Ljava/io/File;[Ljava/security/cert/Certificate;)Z
    //   74: istore_2
    //   75: aload 4
    //   77: invokevirtual 193	java/util/jar/JarFile:close	()V
    //   80: iload_2
    //   81: ireturn
    //   82: astore_1
    //   83: aload 4
    //   85: astore_3
    //   86: goto +43 -> 129
    //   89: astore_3
    //   90: aload 4
    //   92: astore_1
    //   93: aload_3
    //   94: astore 4
    //   96: goto +12 -> 108
    //   99: astore_1
    //   100: goto +29 -> 129
    //   103: astore 4
    //   105: aload 5
    //   107: astore_1
    //   108: aload_1
    //   109: astore_3
    //   110: aload 4
    //   112: ldc 127
    //   114: ldc -50
    //   116: invokestatic 132	com/amap/api/mapcore/util/hd:a	(Ljava/lang/Throwable;Ljava/lang/String;Ljava/lang/String;)V
    //   119: aload_1
    //   120: ifnull +7 -> 127
    //   123: aload_1
    //   124: invokevirtual 193	java/util/jar/JarFile:close	()V
    //   127: iconst_0
    //   128: ireturn
    //   129: aload_3
    //   130: ifnull +7 -> 137
    //   133: aload_3
    //   134: invokevirtual 193	java/util/jar/JarFile:close	()V
    //   137: aload_1
    //   138: athrow
    //   139: astore_1
    //   140: iconst_0
    //   141: ireturn
    //   142: astore_1
    //   143: iconst_0
    //   144: ireturn
    //   145: astore_1
    //   146: iload_2
    //   147: ireturn
    //   148: astore_1
    //   149: iconst_0
    //   150: ireturn
    //   151: astore_3
    //   152: goto -15 -> 137
    // Local variable table:
    //   start	length	slot	name	signature
    //   0	155	0	this	hh
    //   0	155	1	paramFile	File
    //   74	73	2	bool	boolean
    //   8	78	3	localObject1	Object
    //   89	5	3	localThrowable1	Throwable
    //   109	25	3	localFile	File
    //   151	1	3	localThrowable2	Throwable
    //   4	91	4	localObject2	Object
    //   103	8	4	localThrowable3	Throwable
    //   1	105	5	localObject3	Object
    // Exception table:
    //   from	to	target	type
    //   26	34	82	finally
    //   45	57	82	finally
    //   68	75	82	finally
    //   26	34	89	java/lang/Throwable
    //   45	57	89	java/lang/Throwable
    //   68	75	89	java/lang/Throwable
    //   9	13	99	finally
    //   16	26	99	finally
    //   110	119	99	finally
    //   9	13	103	java/lang/Throwable
    //   16	26	103	java/lang/Throwable
    //   38	43	139	java/lang/Throwable
    //   61	66	142	java/lang/Throwable
    //   75	80	145	java/lang/Throwable
    //   123	127	148	java/lang/Throwable
    //   133	137	151	java/lang/Throwable
  }
  
  private boolean a(File paramFile, Certificate[] paramArrayOfCertificate)
  {
    try
    {
      if (paramArrayOfCertificate.length > 0)
      {
        int j = paramArrayOfCertificate.length - 1;
        if (j >= 0)
        {
          paramArrayOfCertificate[j].verify(this.i);
          return true;
        }
      }
    }
    catch (Exception paramFile)
    {
      hd.a(paramFile, "DyLoader", "check");
    }
    return false;
  }
  
  private void b(final Context paramContext, final String paramString1, final String paramString2)
  {
    try
    {
      hb.b().a().submit(new Runnable()
      {
        public void run()
        {
          try
          {
            hh.this.a(paramContext, paramString1, paramString2);
            return;
          }
          catch (Throwable localThrowable)
          {
            hd.a(localThrowable, "dLoader", "run()");
          }
        }
      });
      return;
    }
    catch (Throwable paramContext) {}
  }
  
  private void b(go paramgo, File paramFile)
  {
    this.d = false;
    gw.a(this.a, paramgo, paramFile.getName());
    paramgo = gw.a(this.a, paramgo, this.e);
    if (!TextUtils.isEmpty(paramgo))
    {
      this.f = paramgo;
      gw.a(this.a, this.e);
    }
  }
  
  private void b(String paramString1, String paramString2)
    throws Exception
  {
    if ((!TextUtils.isEmpty(paramString1)) && (!TextUtils.isEmpty(paramString2))) {
      return;
    }
    throw new Exception("dexPath or dexOutputDir is null.");
  }
  
  private void c()
  {
    if (this.i != null) {
      return;
    }
    this.i = hd.a();
  }
  
  void a(Context paramContext, String paramString1, String paramString2)
    throws Exception
  {
    new Date().getTime();
    try
    {
      paramContext = new go(paramContext, gy.a());
      paramString1 = new File(paramString1);
      a(paramContext, paramString1);
      if (!a(paramContext, this.e, paramString1.getAbsolutePath())) {
        b(paramContext, paramString1);
      }
      if (!paramString1.exists()) {
        return;
      }
      StringBuilder localStringBuilder = new StringBuilder();
      localStringBuilder.append(paramString2);
      localStringBuilder.append(File.separator);
      localStringBuilder.append(gw.a(paramString1.getName()));
      if ((new File(localStringBuilder.toString()).exists()) && (!a(paramContext, gw.a(paramString1.getName()), this.f))) {
        gw.a(this.a, this.e);
      }
    }
    catch (Throwable paramContext)
    {
      hd.a(paramContext, "dLoader", "verifyD()");
    }
    new Date().getTime();
  }
  
  /* Error */
  void a(String paramString1, String paramString2)
    throws Exception
  {
    // Byte code:
    //   0: aconst_null
    //   1: astore 5
    //   3: aconst_null
    //   4: astore 4
    //   6: aload 4
    //   8: astore_3
    //   9: aload_0
    //   10: getfield 281	com/amap/api/mapcore/util/hh:c	Ldalvik/system/DexFile;
    //   13: ifnull +4 -> 17
    //   16: return
    //   17: aload 4
    //   19: astore_3
    //   20: invokestatic 46	com/amap/api/mapcore/util/hb:b	()Lcom/amap/api/mapcore/util/hb;
    //   23: aload_0
    //   24: getfield 50	com/amap/api/mapcore/util/hh:e	Lcom/amap/api/mapcore/util/fv;
    //   27: invokevirtual 53	com/amap/api/mapcore/util/hb:a	(Lcom/amap/api/mapcore/util/fv;)Lcom/amap/api/mapcore/util/hb$a;
    //   30: astore 4
    //   32: aload 4
    //   34: ifnull +12 -> 46
    //   37: aload 4
    //   39: iconst_1
    //   40: putfield 283	com/amap/api/mapcore/util/hb$a:a	Z
    //   43: goto +3 -> 46
    //   46: aload_0
    //   47: invokevirtual 285	com/amap/api/mapcore/util/hh:b	()V
    //   50: aload 4
    //   52: getfield 58	com/amap/api/mapcore/util/hb$a:b	Z
    //   55: ifne +43 -> 98
    //   58: aload_0
    //   59: aload_1
    //   60: aload_2
    //   61: iconst_0
    //   62: invokestatic 291	dalvik/system/DexFile:loadDex	(Ljava/lang/String;Ljava/lang/String;I)Ldalvik/system/DexFile;
    //   65: putfield 281	com/amap/api/mapcore/util/hh:c	Ldalvik/system/DexFile;
    //   68: aload 4
    //   70: ifnull +27 -> 97
    //   73: aload 4
    //   75: iconst_0
    //   76: putfield 283	com/amap/api/mapcore/util/hb$a:a	Z
    //   79: aload 4
    //   81: monitorenter
    //   82: aload 4
    //   84: invokevirtual 296	java/lang/Object:notify	()V
    //   87: aload 4
    //   89: monitorexit
    //   90: return
    //   91: astore_1
    //   92: aload 4
    //   94: monitorexit
    //   95: aload_1
    //   96: athrow
    //   97: return
    //   98: new 12	java/lang/Exception
    //   101: dup
    //   102: ldc 87
    //   104: invokespecial 88	java/lang/Exception:<init>	(Ljava/lang/String;)V
    //   107: athrow
    //   108: astore_1
    //   109: goto +32 -> 141
    //   112: astore_2
    //   113: aload 5
    //   115: astore_1
    //   116: aload_1
    //   117: astore_3
    //   118: aload_2
    //   119: ldc_w 276
    //   122: ldc_w 298
    //   125: invokestatic 132	com/amap/api/mapcore/util/hd:a	(Ljava/lang/Throwable;Ljava/lang/String;Ljava/lang/String;)V
    //   128: aload_1
    //   129: astore_3
    //   130: new 12	java/lang/Exception
    //   133: dup
    //   134: ldc_w 300
    //   137: invokespecial 88	java/lang/Exception:<init>	(Ljava/lang/String;)V
    //   140: athrow
    //   141: aload_3
    //   142: ifnull +24 -> 166
    //   145: aload_3
    //   146: iconst_0
    //   147: putfield 283	com/amap/api/mapcore/util/hb$a:a	Z
    //   150: aload_3
    //   151: monitorenter
    //   152: aload_3
    //   153: invokevirtual 296	java/lang/Object:notify	()V
    //   156: aload_3
    //   157: monitorexit
    //   158: goto +8 -> 166
    //   161: astore_2
    //   162: aload_3
    //   163: monitorexit
    //   164: aload_2
    //   165: athrow
    //   166: aload_1
    //   167: athrow
    //   168: astore_1
    //   169: return
    //   170: astore_2
    //   171: goto -5 -> 166
    //   174: astore_1
    //   175: aload 4
    //   177: astore_3
    //   178: goto -37 -> 141
    //   181: astore_2
    //   182: aload 4
    //   184: astore_1
    //   185: goto -69 -> 116
    // Local variable table:
    //   start	length	slot	name	signature
    //   0	188	0	this	hh
    //   0	188	1	paramString1	String
    //   0	188	2	paramString2	String
    //   8	170	3	localObject1	Object
    //   4	179	4	locala	hb.a
    //   1	113	5	localObject2	Object
    // Exception table:
    //   from	to	target	type
    //   82	90	91	finally
    //   92	95	91	finally
    //   9	16	108	finally
    //   20	32	108	finally
    //   118	128	108	finally
    //   130	141	108	finally
    //   9	16	112	java/lang/Throwable
    //   20	32	112	java/lang/Throwable
    //   152	158	161	finally
    //   162	164	161	finally
    //   73	82	168	java/lang/Throwable
    //   95	97	168	java/lang/Throwable
    //   145	152	170	java/lang/Throwable
    //   164	166	170	java/lang/Throwable
    //   37	43	174	finally
    //   46	68	174	finally
    //   98	108	174	finally
    //   37	43	181	java/lang/Throwable
    //   46	68	181	java/lang/Throwable
    //   98	108	181	java/lang/Throwable
  }
  
  /* Error */
  protected Class<?> findClass(String paramString)
    throws java.lang.ClassNotFoundException
  {
    // Byte code:
    //   0: aload_0
    //   1: getfield 281	com/amap/api/mapcore/util/hh:c	Ldalvik/system/DexFile;
    //   4: astore_2
    //   5: aload_2
    //   6: ifnull +203 -> 209
    //   9: aconst_null
    //   10: astore 4
    //   12: aconst_null
    //   13: astore_3
    //   14: aload 4
    //   16: astore_2
    //   17: aload_0
    //   18: getfield 307	com/amap/api/mapcore/util/hh:b	Ljava/util/Map;
    //   21: astore 5
    //   23: aload 4
    //   25: astore_2
    //   26: aload 5
    //   28: monitorenter
    //   29: aload_0
    //   30: getfield 307	com/amap/api/mapcore/util/hh:b	Ljava/util/Map;
    //   33: aload_1
    //   34: invokeinterface 313 2 0
    //   39: checkcast 315	java/lang/Class
    //   42: astore_2
    //   43: aload 5
    //   45: monitorexit
    //   46: goto +33 -> 79
    //   49: astore_3
    //   50: aload_3
    //   51: astore 4
    //   53: goto +7 -> 60
    //   56: astore 4
    //   58: aload_3
    //   59: astore_2
    //   60: aload_2
    //   61: astore_3
    //   62: aload 5
    //   64: monitorexit
    //   65: aload 4
    //   67: athrow
    //   68: astore_3
    //   69: aload_3
    //   70: ldc_w 276
    //   73: ldc_w 317
    //   76: invokestatic 132	com/amap/api/mapcore/util/hd:a	(Ljava/lang/Throwable;Ljava/lang/String;Ljava/lang/String;)V
    //   79: aload_2
    //   80: ifnull +10 -> 90
    //   83: aload_0
    //   84: iconst_0
    //   85: putfield 320	com/amap/api/mapcore/util/hh:h	Z
    //   88: aload_2
    //   89: areturn
    //   90: aload_0
    //   91: getfield 323	com/amap/api/mapcore/util/hh:g	Z
    //   94: ifne +106 -> 200
    //   97: aload_0
    //   98: iconst_1
    //   99: putfield 320	com/amap/api/mapcore/util/hh:h	Z
    //   102: aload_0
    //   103: getfield 281	com/amap/api/mapcore/util/hh:c	Ldalvik/system/DexFile;
    //   106: aload_1
    //   107: aload_0
    //   108: invokevirtual 327	dalvik/system/DexFile:loadClass	(Ljava/lang/String;Ljava/lang/ClassLoader;)Ljava/lang/Class;
    //   111: astore_2
    //   112: aload_0
    //   113: getfield 281	com/amap/api/mapcore/util/hh:c	Ldalvik/system/DexFile;
    //   116: astore_3
    //   117: aload_3
    //   118: monitorenter
    //   119: aload_0
    //   120: getfield 281	com/amap/api/mapcore/util/hh:c	Ldalvik/system/DexFile;
    //   123: invokevirtual 296	java/lang/Object:notify	()V
    //   126: aload_3
    //   127: monitorexit
    //   128: aload_0
    //   129: iconst_0
    //   130: putfield 320	com/amap/api/mapcore/util/hh:h	Z
    //   133: aload_2
    //   134: ifnull +52 -> 186
    //   137: aload_0
    //   138: getfield 307	com/amap/api/mapcore/util/hh:b	Ljava/util/Map;
    //   141: astore_3
    //   142: aload_3
    //   143: monitorenter
    //   144: aload_0
    //   145: getfield 307	com/amap/api/mapcore/util/hh:b	Ljava/util/Map;
    //   148: aload_1
    //   149: aload_2
    //   150: invokeinterface 331 3 0
    //   155: pop
    //   156: aload_3
    //   157: monitorexit
    //   158: goto +21 -> 179
    //   161: astore 4
    //   163: aload_3
    //   164: monitorexit
    //   165: aload 4
    //   167: athrow
    //   168: astore_3
    //   169: aload_3
    //   170: ldc_w 276
    //   173: ldc_w 317
    //   176: invokestatic 132	com/amap/api/mapcore/util/hd:a	(Ljava/lang/Throwable;Ljava/lang/String;Ljava/lang/String;)V
    //   179: aload_0
    //   180: iconst_0
    //   181: putfield 320	com/amap/api/mapcore/util/hh:h	Z
    //   184: aload_2
    //   185: areturn
    //   186: new 304	java/lang/ClassNotFoundException
    //   189: dup
    //   190: aload_1
    //   191: invokespecial 332	java/lang/ClassNotFoundException:<init>	(Ljava/lang/String;)V
    //   194: athrow
    //   195: astore_2
    //   196: aload_3
    //   197: monitorexit
    //   198: aload_2
    //   199: athrow
    //   200: new 304	java/lang/ClassNotFoundException
    //   203: dup
    //   204: aload_1
    //   205: invokespecial 332	java/lang/ClassNotFoundException:<init>	(Ljava/lang/String;)V
    //   208: athrow
    //   209: new 304	java/lang/ClassNotFoundException
    //   212: dup
    //   213: aload_1
    //   214: invokespecial 332	java/lang/ClassNotFoundException:<init>	(Ljava/lang/String;)V
    //   217: athrow
    //   218: astore_1
    //   219: goto +26 -> 245
    //   222: astore_2
    //   223: aload_2
    //   224: ldc_w 276
    //   227: ldc_w 317
    //   230: invokestatic 132	com/amap/api/mapcore/util/hd:a	(Ljava/lang/Throwable;Ljava/lang/String;Ljava/lang/String;)V
    //   233: new 304	java/lang/ClassNotFoundException
    //   236: dup
    //   237: aload_1
    //   238: invokespecial 332	java/lang/ClassNotFoundException:<init>	(Ljava/lang/String;)V
    //   241: athrow
    //   242: astore_1
    //   243: aload_1
    //   244: athrow
    //   245: aload_0
    //   246: iconst_0
    //   247: putfield 320	com/amap/api/mapcore/util/hh:h	Z
    //   250: aload_1
    //   251: athrow
    // Local variable table:
    //   start	length	slot	name	signature
    //   0	252	0	this	hh
    //   0	252	1	paramString	String
    //   4	181	2	localObject1	Object
    //   195	4	2	localObject2	Object
    //   222	2	2	localThrowable1	Throwable
    //   13	1	3	localObject3	Object
    //   49	10	3	localObject4	Object
    //   61	1	3	localObject5	Object
    //   68	2	3	localThrowable2	Throwable
    //   168	29	3	localThrowable3	Throwable
    //   10	42	4	localObject7	Object
    //   56	10	4	localObject8	Object
    //   161	5	4	localObject9	Object
    //   21	42	5	localMap	java.util.Map
    // Exception table:
    //   from	to	target	type
    //   43	46	49	finally
    //   29	43	56	finally
    //   62	65	56	finally
    //   17	23	68	java/lang/Throwable
    //   26	29	68	java/lang/Throwable
    //   65	68	68	java/lang/Throwable
    //   144	158	161	finally
    //   163	165	161	finally
    //   137	144	168	java/lang/Throwable
    //   165	168	168	java/lang/Throwable
    //   119	128	195	finally
    //   196	198	195	finally
    //   0	5	218	finally
    //   17	23	218	finally
    //   26	29	218	finally
    //   65	68	218	finally
    //   69	79	218	finally
    //   90	119	218	finally
    //   128	133	218	finally
    //   137	144	218	finally
    //   165	168	218	finally
    //   169	179	218	finally
    //   186	195	218	finally
    //   198	200	218	finally
    //   200	209	218	finally
    //   209	218	218	finally
    //   223	242	218	finally
    //   243	245	218	finally
    //   0	5	222	java/lang/Throwable
    //   69	79	222	java/lang/Throwable
    //   90	119	222	java/lang/Throwable
    //   128	133	222	java/lang/Throwable
    //   169	179	222	java/lang/Throwable
    //   186	195	222	java/lang/Throwable
    //   198	200	222	java/lang/Throwable
    //   200	209	222	java/lang/Throwable
    //   209	218	222	java/lang/Throwable
    //   0	5	242	java/lang/ClassNotFoundException
    //   17	23	242	java/lang/ClassNotFoundException
    //   26	29	242	java/lang/ClassNotFoundException
    //   65	68	242	java/lang/ClassNotFoundException
    //   69	79	242	java/lang/ClassNotFoundException
    //   90	119	242	java/lang/ClassNotFoundException
    //   128	133	242	java/lang/ClassNotFoundException
    //   137	144	242	java/lang/ClassNotFoundException
    //   165	168	242	java/lang/ClassNotFoundException
    //   169	179	242	java/lang/ClassNotFoundException
    //   186	195	242	java/lang/ClassNotFoundException
    //   198	200	242	java/lang/ClassNotFoundException
    //   200	209	242	java/lang/ClassNotFoundException
    //   209	218	242	java/lang/ClassNotFoundException
  }
}


/* Location:              C:\Users\lixia\Desktop\android反编译三件套\dex2jar-2.0\classes-dex2jar.jar!\com\amap\api\mapcore\util\hh.class
 * Java compiler version: 6 (50.0)
 * JD-Core Version:       0.7.1
 */