package com.amap.api.mapcore.util;

import android.content.Context;
import android.text.TextUtils;
import java.util.List;
import java.util.Map;
import org.json.JSONObject;

public final class kt
{
  private StringBuilder a = new StringBuilder();
  
  public final le a(String paramString, Context paramContext, ie paramie)
  {
    le localle = new le("");
    localle.setErrorCode(7);
    try
    {
      localObject1 = new JSONObject(paramString);
      if ((!((JSONObject)localObject1).has("status")) || (!((JSONObject)localObject1).has("info")))
      {
        localObject2 = this.a;
        StringBuilder localStringBuilder = new StringBuilder("json is error ");
        localStringBuilder.append(paramString);
        ((StringBuilder)localObject2).append(localStringBuilder.toString());
      }
      localObject2 = ((JSONObject)localObject1).getString("status");
      paramString = ((JSONObject)localObject1).getString("info");
      if (((String)localObject2).equals("0"))
      {
        localObject1 = this.a;
        localObject2 = new StringBuilder("auth fail:");
        ((StringBuilder)localObject2).append(paramString);
        ((StringBuilder)localObject1).append(((StringBuilder)localObject2).toString());
      }
    }
    catch (Throwable paramString)
    {
      Object localObject1 = this.a;
      Object localObject2 = new StringBuilder("json exception error:");
      ((StringBuilder)localObject2).append(paramString.getMessage());
      ((StringBuilder)localObject1).append(((StringBuilder)localObject2).toString());
      lf.a(paramString, "MapParser", "paseAuthFailurJson");
    }
    try
    {
      paramString = this.a;
      paramString.append("#SHA1AndPackage#");
      paramString.append(fk.e(paramContext));
      paramString = (String)((List)paramie.b.get("gsid")).get(0);
      if (!TextUtils.isEmpty(paramString))
      {
        paramContext = this.a;
        paramContext.append(" #gsid#");
        paramContext.append(paramString);
      }
      paramString = paramie.c;
      if (!TextUtils.isEmpty(paramString))
      {
        paramContext = this.a;
        paramie = new StringBuilder(" #csid#");
        paramie.append(paramString);
        paramContext.append(paramie.toString());
      }
    }
    catch (Throwable paramString)
    {
      for (;;) {}
    }
    localle.setLocationDetail(this.a.toString());
    if (this.a.length() > 0) {
      this.a.delete(0, this.a.length());
    }
    return localle;
  }
  
  /* Error */
  public final le a(byte[] paramArrayOfByte)
  {
    // Byte code:
    //   0: new 21	com/amap/api/mapcore/util/le
    //   3: dup
    //   4: ldc 23
    //   6: invokespecial 26	com/amap/api/mapcore/util/le:<init>	(Ljava/lang/String;)V
    //   9: astore 6
    //   11: aload_1
    //   12: ifnonnull +50 -> 62
    //   15: aload 6
    //   17: iconst_5
    //   18: invokevirtual 30	com/amap/api/mapcore/util/le:setErrorCode	(I)V
    //   21: aload_0
    //   22: getfield 15	com/amap/api/mapcore/util/kt:a	Ljava/lang/StringBuilder;
    //   25: ldc -121
    //   27: invokevirtual 48	java/lang/StringBuilder:append	(Ljava/lang/String;)Ljava/lang/StringBuilder;
    //   30: pop
    //   31: aload 6
    //   33: aload_0
    //   34: getfield 15	com/amap/api/mapcore/util/kt:a	Ljava/lang/StringBuilder;
    //   37: invokevirtual 52	java/lang/StringBuilder:toString	()Ljava/lang/String;
    //   40: invokevirtual 124	com/amap/api/mapcore/util/le:setLocationDetail	(Ljava/lang/String;)V
    //   43: aload_0
    //   44: getfield 15	com/amap/api/mapcore/util/kt:a	Ljava/lang/StringBuilder;
    //   47: iconst_0
    //   48: aload_0
    //   49: getfield 15	com/amap/api/mapcore/util/kt:a	Ljava/lang/StringBuilder;
    //   52: invokevirtual 128	java/lang/StringBuilder:length	()I
    //   55: invokevirtual 132	java/lang/StringBuilder:delete	(II)Ljava/lang/StringBuilder;
    //   58: pop
    //   59: aload 6
    //   61: areturn
    //   62: aload_1
    //   63: invokestatic 141	java/nio/ByteBuffer:wrap	([B)Ljava/nio/ByteBuffer;
    //   66: astore_1
    //   67: aload_1
    //   68: astore 5
    //   70: aload_1
    //   71: invokevirtual 144	java/nio/ByteBuffer:get	()B
    //   74: ifne +38 -> 112
    //   77: aload_1
    //   78: astore 5
    //   80: aload 6
    //   82: aload_1
    //   83: invokevirtual 148	java/nio/ByteBuffer:getShort	()S
    //   86: invokestatic 152	java/lang/String:valueOf	(I)Ljava/lang/String;
    //   89: invokevirtual 154	com/amap/api/mapcore/util/le:b	(Ljava/lang/String;)V
    //   92: aload_1
    //   93: astore 5
    //   95: aload_1
    //   96: invokevirtual 158	java/nio/ByteBuffer:clear	()Ljava/nio/Buffer;
    //   99: pop
    //   100: aload_1
    //   101: ifnull +8 -> 109
    //   104: aload_1
    //   105: invokevirtual 158	java/nio/ByteBuffer:clear	()Ljava/nio/Buffer;
    //   108: pop
    //   109: aload 6
    //   111: areturn
    //   112: aload_1
    //   113: astore 5
    //   115: aload_1
    //   116: invokevirtual 161	java/nio/ByteBuffer:getInt	()I
    //   119: istore 4
    //   121: iload 4
    //   123: i2d
    //   124: dstore_2
    //   125: dload_2
    //   126: invokestatic 167	java/lang/Double:isNaN	(D)Z
    //   129: pop
    //   130: dload_2
    //   131: ldc2_w 168
    //   134: ddiv
    //   135: dstore_2
    //   136: aload_1
    //   137: astore 5
    //   139: aload 6
    //   141: dload_2
    //   142: invokestatic 174	com/amap/api/mapcore/util/lj:a	(D)D
    //   145: invokevirtual 178	com/amap/api/mapcore/util/le:setLongitude	(D)V
    //   148: aload_1
    //   149: astore 5
    //   151: aload_1
    //   152: invokevirtual 161	java/nio/ByteBuffer:getInt	()I
    //   155: istore 4
    //   157: iload 4
    //   159: i2d
    //   160: dstore_2
    //   161: dload_2
    //   162: invokestatic 167	java/lang/Double:isNaN	(D)Z
    //   165: pop
    //   166: dload_2
    //   167: ldc2_w 168
    //   170: ddiv
    //   171: dstore_2
    //   172: aload_1
    //   173: astore 5
    //   175: aload 6
    //   177: dload_2
    //   178: invokestatic 174	com/amap/api/mapcore/util/lj:a	(D)D
    //   181: invokevirtual 181	com/amap/api/mapcore/util/le:setLatitude	(D)V
    //   184: aload_1
    //   185: astore 5
    //   187: aload 6
    //   189: aload_1
    //   190: invokevirtual 148	java/nio/ByteBuffer:getShort	()S
    //   193: i2f
    //   194: invokevirtual 185	com/amap/api/mapcore/util/le:setAccuracy	(F)V
    //   197: aload_1
    //   198: astore 5
    //   200: aload 6
    //   202: aload_1
    //   203: invokevirtual 144	java/nio/ByteBuffer:get	()B
    //   206: invokestatic 152	java/lang/String:valueOf	(I)Ljava/lang/String;
    //   209: invokevirtual 187	com/amap/api/mapcore/util/le:c	(Ljava/lang/String;)V
    //   212: aload_1
    //   213: astore 5
    //   215: aload 6
    //   217: aload_1
    //   218: invokevirtual 144	java/nio/ByteBuffer:get	()B
    //   221: invokestatic 152	java/lang/String:valueOf	(I)Ljava/lang/String;
    //   224: invokevirtual 190	com/amap/api/mapcore/util/le:d	(Ljava/lang/String;)V
    //   227: aload_1
    //   228: astore 5
    //   230: aload_1
    //   231: invokevirtual 144	java/nio/ByteBuffer:get	()B
    //   234: iconst_1
    //   235: if_icmpne +914 -> 1149
    //   238: aload_1
    //   239: astore 5
    //   241: aload_1
    //   242: invokevirtual 144	java/nio/ByteBuffer:get	()B
    //   245: sipush 255
    //   248: iand
    //   249: newarray <illegal type>
    //   251: astore 7
    //   253: aload_1
    //   254: astore 5
    //   256: aload_1
    //   257: aload 7
    //   259: invokevirtual 192	java/nio/ByteBuffer:get	([B)Ljava/nio/ByteBuffer;
    //   262: pop
    //   263: aload_1
    //   264: astore 5
    //   266: aload 6
    //   268: new 60	java/lang/String
    //   271: dup
    //   272: aload 7
    //   274: ldc -62
    //   276: invokespecial 197	java/lang/String:<init>	([BLjava/lang/String;)V
    //   279: invokevirtual 200	com/amap/api/mapcore/util/le:setCountry	(Ljava/lang/String;)V
    //   282: aload_1
    //   283: astore 5
    //   285: aload_1
    //   286: invokevirtual 144	java/nio/ByteBuffer:get	()B
    //   289: sipush 255
    //   292: iand
    //   293: newarray <illegal type>
    //   295: astore 7
    //   297: aload_1
    //   298: astore 5
    //   300: aload_1
    //   301: aload 7
    //   303: invokevirtual 192	java/nio/ByteBuffer:get	([B)Ljava/nio/ByteBuffer;
    //   306: pop
    //   307: aload_1
    //   308: astore 5
    //   310: new 60	java/lang/String
    //   313: dup
    //   314: aload 7
    //   316: ldc -62
    //   318: invokespecial 197	java/lang/String:<init>	([BLjava/lang/String;)V
    //   321: astore 7
    //   323: aload_1
    //   324: astore 5
    //   326: aload 6
    //   328: aload 7
    //   330: invokevirtual 203	com/amap/api/mapcore/util/le:setProvince	(Ljava/lang/String;)V
    //   333: goto +7 -> 340
    //   336: ldc 23
    //   338: astore 7
    //   340: aload_1
    //   341: astore 5
    //   343: aload_1
    //   344: invokevirtual 144	java/nio/ByteBuffer:get	()B
    //   347: sipush 255
    //   350: iand
    //   351: newarray <illegal type>
    //   353: astore 8
    //   355: aload_1
    //   356: astore 5
    //   358: aload_1
    //   359: aload 8
    //   361: invokevirtual 192	java/nio/ByteBuffer:get	([B)Ljava/nio/ByteBuffer;
    //   364: pop
    //   365: aload_1
    //   366: astore 5
    //   368: new 60	java/lang/String
    //   371: dup
    //   372: aload 8
    //   374: ldc -62
    //   376: invokespecial 197	java/lang/String:<init>	([BLjava/lang/String;)V
    //   379: astore 8
    //   381: aload_1
    //   382: astore 5
    //   384: aload 6
    //   386: aload 8
    //   388: invokevirtual 206	com/amap/api/mapcore/util/le:setCity	(Ljava/lang/String;)V
    //   391: goto +7 -> 398
    //   394: ldc 23
    //   396: astore 8
    //   398: aload_1
    //   399: astore 5
    //   401: aload_1
    //   402: invokevirtual 144	java/nio/ByteBuffer:get	()B
    //   405: sipush 255
    //   408: iand
    //   409: newarray <illegal type>
    //   411: astore 9
    //   413: aload_1
    //   414: astore 5
    //   416: aload_1
    //   417: aload 9
    //   419: invokevirtual 192	java/nio/ByteBuffer:get	([B)Ljava/nio/ByteBuffer;
    //   422: pop
    //   423: aload_1
    //   424: astore 5
    //   426: new 60	java/lang/String
    //   429: dup
    //   430: aload 9
    //   432: ldc -62
    //   434: invokespecial 197	java/lang/String:<init>	([BLjava/lang/String;)V
    //   437: astore 9
    //   439: aload_1
    //   440: astore 5
    //   442: aload 6
    //   444: aload 9
    //   446: invokevirtual 209	com/amap/api/mapcore/util/le:setDistrict	(Ljava/lang/String;)V
    //   449: goto +7 -> 456
    //   452: ldc 23
    //   454: astore 9
    //   456: aload_1
    //   457: astore 5
    //   459: aload_1
    //   460: invokevirtual 144	java/nio/ByteBuffer:get	()B
    //   463: sipush 255
    //   466: iand
    //   467: newarray <illegal type>
    //   469: astore 10
    //   471: aload_1
    //   472: astore 5
    //   474: aload_1
    //   475: aload 10
    //   477: invokevirtual 192	java/nio/ByteBuffer:get	([B)Ljava/nio/ByteBuffer;
    //   480: pop
    //   481: aload_1
    //   482: astore 5
    //   484: new 60	java/lang/String
    //   487: dup
    //   488: aload 10
    //   490: ldc -62
    //   492: invokespecial 197	java/lang/String:<init>	([BLjava/lang/String;)V
    //   495: astore 10
    //   497: aload_1
    //   498: astore 5
    //   500: aload 6
    //   502: aload 10
    //   504: invokevirtual 212	com/amap/api/mapcore/util/le:setStreet	(Ljava/lang/String;)V
    //   507: aload_1
    //   508: astore 5
    //   510: aload 6
    //   512: aload 10
    //   514: invokevirtual 215	com/amap/api/mapcore/util/le:setRoad	(Ljava/lang/String;)V
    //   517: goto +7 -> 524
    //   520: ldc 23
    //   522: astore 10
    //   524: aload_1
    //   525: astore 5
    //   527: aload_1
    //   528: invokevirtual 144	java/nio/ByteBuffer:get	()B
    //   531: sipush 255
    //   534: iand
    //   535: newarray <illegal type>
    //   537: astore 11
    //   539: aload_1
    //   540: astore 5
    //   542: aload_1
    //   543: aload 11
    //   545: invokevirtual 192	java/nio/ByteBuffer:get	([B)Ljava/nio/ByteBuffer;
    //   548: pop
    //   549: aload_1
    //   550: astore 5
    //   552: aload 6
    //   554: new 60	java/lang/String
    //   557: dup
    //   558: aload 11
    //   560: ldc -62
    //   562: invokespecial 197	java/lang/String:<init>	([BLjava/lang/String;)V
    //   565: invokevirtual 218	com/amap/api/mapcore/util/le:setNumber	(Ljava/lang/String;)V
    //   568: aload_1
    //   569: astore 5
    //   571: aload_1
    //   572: invokevirtual 144	java/nio/ByteBuffer:get	()B
    //   575: sipush 255
    //   578: iand
    //   579: newarray <illegal type>
    //   581: astore 11
    //   583: aload_1
    //   584: astore 5
    //   586: aload_1
    //   587: aload 11
    //   589: invokevirtual 192	java/nio/ByteBuffer:get	([B)Ljava/nio/ByteBuffer;
    //   592: pop
    //   593: aload_1
    //   594: astore 5
    //   596: new 60	java/lang/String
    //   599: dup
    //   600: aload 11
    //   602: ldc -62
    //   604: invokespecial 197	java/lang/String:<init>	([BLjava/lang/String;)V
    //   607: astore 11
    //   609: aload_1
    //   610: astore 5
    //   612: aload 6
    //   614: aload 11
    //   616: invokevirtual 221	com/amap/api/mapcore/util/le:setPoiName	(Ljava/lang/String;)V
    //   619: goto +7 -> 626
    //   622: ldc 23
    //   624: astore 11
    //   626: aload_1
    //   627: astore 5
    //   629: aload_1
    //   630: invokevirtual 144	java/nio/ByteBuffer:get	()B
    //   633: sipush 255
    //   636: iand
    //   637: newarray <illegal type>
    //   639: astore 12
    //   641: aload_1
    //   642: astore 5
    //   644: aload_1
    //   645: aload 12
    //   647: invokevirtual 192	java/nio/ByteBuffer:get	([B)Ljava/nio/ByteBuffer;
    //   650: pop
    //   651: aload_1
    //   652: astore 5
    //   654: aload 6
    //   656: new 60	java/lang/String
    //   659: dup
    //   660: aload 12
    //   662: ldc -62
    //   664: invokespecial 197	java/lang/String:<init>	([BLjava/lang/String;)V
    //   667: invokevirtual 224	com/amap/api/mapcore/util/le:setAoiName	(Ljava/lang/String;)V
    //   670: aload_1
    //   671: astore 5
    //   673: aload_1
    //   674: invokevirtual 144	java/nio/ByteBuffer:get	()B
    //   677: sipush 255
    //   680: iand
    //   681: newarray <illegal type>
    //   683: astore 12
    //   685: aload_1
    //   686: astore 5
    //   688: aload_1
    //   689: aload 12
    //   691: invokevirtual 192	java/nio/ByteBuffer:get	([B)Ljava/nio/ByteBuffer;
    //   694: pop
    //   695: aload_1
    //   696: astore 5
    //   698: new 60	java/lang/String
    //   701: dup
    //   702: aload 12
    //   704: ldc -62
    //   706: invokespecial 197	java/lang/String:<init>	([BLjava/lang/String;)V
    //   709: astore 12
    //   711: aload_1
    //   712: astore 5
    //   714: aload 6
    //   716: aload 12
    //   718: invokevirtual 227	com/amap/api/mapcore/util/le:setAdCode	(Ljava/lang/String;)V
    //   721: goto +7 -> 728
    //   724: ldc 23
    //   726: astore 12
    //   728: aload_1
    //   729: astore 5
    //   731: aload_1
    //   732: invokevirtual 144	java/nio/ByteBuffer:get	()B
    //   735: sipush 255
    //   738: iand
    //   739: newarray <illegal type>
    //   741: astore 13
    //   743: aload_1
    //   744: astore 5
    //   746: aload_1
    //   747: aload 13
    //   749: invokevirtual 192	java/nio/ByteBuffer:get	([B)Ljava/nio/ByteBuffer;
    //   752: pop
    //   753: aload_1
    //   754: astore 5
    //   756: aload 6
    //   758: new 60	java/lang/String
    //   761: dup
    //   762: aload 13
    //   764: ldc -62
    //   766: invokespecial 197	java/lang/String:<init>	([BLjava/lang/String;)V
    //   769: invokevirtual 230	com/amap/api/mapcore/util/le:setCityCode	(Ljava/lang/String;)V
    //   772: aload_1
    //   773: astore 5
    //   775: new 12	java/lang/StringBuilder
    //   778: dup
    //   779: invokespecial 13	java/lang/StringBuilder:<init>	()V
    //   782: astore 13
    //   784: aload_1
    //   785: astore 5
    //   787: aload 7
    //   789: invokestatic 113	android/text/TextUtils:isEmpty	(Ljava/lang/CharSequence;)Z
    //   792: ifne +25 -> 817
    //   795: aload_1
    //   796: astore 5
    //   798: aload 13
    //   800: aload 7
    //   802: invokevirtual 48	java/lang/StringBuilder:append	(Ljava/lang/String;)Ljava/lang/StringBuilder;
    //   805: pop
    //   806: aload_1
    //   807: astore 5
    //   809: aload 13
    //   811: ldc -24
    //   813: invokevirtual 48	java/lang/StringBuilder:append	(Ljava/lang/String;)Ljava/lang/StringBuilder;
    //   816: pop
    //   817: aload_1
    //   818: astore 5
    //   820: aload 8
    //   822: invokestatic 113	android/text/TextUtils:isEmpty	(Ljava/lang/CharSequence;)Z
    //   825: ifne +51 -> 876
    //   828: aload_1
    //   829: astore 5
    //   831: aload 7
    //   833: ldc -22
    //   835: invokevirtual 237	java/lang/String:contains	(Ljava/lang/CharSequence;)Z
    //   838: ifeq +16 -> 854
    //   841: aload_1
    //   842: astore 5
    //   844: aload 7
    //   846: aload 8
    //   848: invokevirtual 64	java/lang/String:equals	(Ljava/lang/Object;)Z
    //   851: ifne +25 -> 876
    //   854: aload_1
    //   855: astore 5
    //   857: aload 13
    //   859: aload 8
    //   861: invokevirtual 48	java/lang/StringBuilder:append	(Ljava/lang/String;)Ljava/lang/StringBuilder;
    //   864: pop
    //   865: aload_1
    //   866: astore 5
    //   868: aload 13
    //   870: ldc -24
    //   872: invokevirtual 48	java/lang/StringBuilder:append	(Ljava/lang/String;)Ljava/lang/StringBuilder;
    //   875: pop
    //   876: aload_1
    //   877: astore 5
    //   879: aload 9
    //   881: invokestatic 113	android/text/TextUtils:isEmpty	(Ljava/lang/CharSequence;)Z
    //   884: ifne +25 -> 909
    //   887: aload_1
    //   888: astore 5
    //   890: aload 13
    //   892: aload 9
    //   894: invokevirtual 48	java/lang/StringBuilder:append	(Ljava/lang/String;)Ljava/lang/StringBuilder;
    //   897: pop
    //   898: aload_1
    //   899: astore 5
    //   901: aload 13
    //   903: ldc -24
    //   905: invokevirtual 48	java/lang/StringBuilder:append	(Ljava/lang/String;)Ljava/lang/StringBuilder;
    //   908: pop
    //   909: aload_1
    //   910: astore 5
    //   912: aload 10
    //   914: invokestatic 113	android/text/TextUtils:isEmpty	(Ljava/lang/CharSequence;)Z
    //   917: ifne +25 -> 942
    //   920: aload_1
    //   921: astore 5
    //   923: aload 13
    //   925: aload 10
    //   927: invokevirtual 48	java/lang/StringBuilder:append	(Ljava/lang/String;)Ljava/lang/StringBuilder;
    //   930: pop
    //   931: aload_1
    //   932: astore 5
    //   934: aload 13
    //   936: ldc -24
    //   938: invokevirtual 48	java/lang/StringBuilder:append	(Ljava/lang/String;)Ljava/lang/StringBuilder;
    //   941: pop
    //   942: aload_1
    //   943: astore 5
    //   945: aload 11
    //   947: invokestatic 113	android/text/TextUtils:isEmpty	(Ljava/lang/CharSequence;)Z
    //   950: ifne +47 -> 997
    //   953: aload_1
    //   954: astore 5
    //   956: aload 12
    //   958: invokestatic 113	android/text/TextUtils:isEmpty	(Ljava/lang/CharSequence;)Z
    //   961: ifne +14 -> 975
    //   964: aload_1
    //   965: astore 5
    //   967: aload 13
    //   969: ldc -17
    //   971: invokevirtual 48	java/lang/StringBuilder:append	(Ljava/lang/String;)Ljava/lang/StringBuilder;
    //   974: pop
    //   975: aload_1
    //   976: astore 5
    //   978: aload 13
    //   980: aload 11
    //   982: invokevirtual 48	java/lang/StringBuilder:append	(Ljava/lang/String;)Ljava/lang/StringBuilder;
    //   985: pop
    //   986: aload_1
    //   987: astore 5
    //   989: aload 13
    //   991: ldc -24
    //   993: invokevirtual 48	java/lang/StringBuilder:append	(Ljava/lang/String;)Ljava/lang/StringBuilder;
    //   996: pop
    //   997: aload_1
    //   998: astore 5
    //   1000: new 241	android/os/Bundle
    //   1003: dup
    //   1004: invokespecial 242	android/os/Bundle:<init>	()V
    //   1007: astore 7
    //   1009: aload_1
    //   1010: astore 5
    //   1012: aload 7
    //   1014: ldc -12
    //   1016: aload 6
    //   1018: invokevirtual 247	com/amap/api/mapcore/util/le:getCityCode	()Ljava/lang/String;
    //   1021: invokevirtual 251	android/os/Bundle:putString	(Ljava/lang/String;Ljava/lang/String;)V
    //   1024: aload_1
    //   1025: astore 5
    //   1027: aload 7
    //   1029: ldc -3
    //   1031: aload 13
    //   1033: invokevirtual 52	java/lang/StringBuilder:toString	()Ljava/lang/String;
    //   1036: invokevirtual 251	android/os/Bundle:putString	(Ljava/lang/String;Ljava/lang/String;)V
    //   1039: aload_1
    //   1040: astore 5
    //   1042: aload 7
    //   1044: ldc -1
    //   1046: aload 6
    //   1048: invokevirtual 258	com/amap/api/mapcore/util/le:getAdCode	()Ljava/lang/String;
    //   1051: invokevirtual 251	android/os/Bundle:putString	(Ljava/lang/String;Ljava/lang/String;)V
    //   1054: aload_1
    //   1055: astore 5
    //   1057: aload 6
    //   1059: aload 7
    //   1061: invokevirtual 262	com/amap/api/mapcore/util/le:setExtras	(Landroid/os/Bundle;)V
    //   1064: aload_1
    //   1065: astore 5
    //   1067: aload 6
    //   1069: aload 13
    //   1071: invokevirtual 52	java/lang/StringBuilder:toString	()Ljava/lang/String;
    //   1074: invokevirtual 264	com/amap/api/mapcore/util/le:e	(Ljava/lang/String;)V
    //   1077: aload_1
    //   1078: astore 5
    //   1080: aload 6
    //   1082: invokevirtual 258	com/amap/api/mapcore/util/le:getAdCode	()Ljava/lang/String;
    //   1085: astore 7
    //   1087: aload 7
    //   1089: ifnull +47 -> 1136
    //   1092: aload_1
    //   1093: astore 5
    //   1095: aload 7
    //   1097: invokevirtual 267	java/lang/String:trim	()Ljava/lang/String;
    //   1100: invokevirtual 268	java/lang/String:length	()I
    //   1103: ifle +33 -> 1136
    //   1106: aload_1
    //   1107: astore 5
    //   1109: aload 13
    //   1111: invokevirtual 52	java/lang/StringBuilder:toString	()Ljava/lang/String;
    //   1114: ldc -24
    //   1116: ldc 23
    //   1118: invokevirtual 272	java/lang/String:replace	(Ljava/lang/CharSequence;Ljava/lang/CharSequence;)Ljava/lang/String;
    //   1121: astore 7
    //   1123: aload_1
    //   1124: astore 5
    //   1126: aload 6
    //   1128: aload 7
    //   1130: invokevirtual 275	com/amap/api/mapcore/util/le:setAddress	(Ljava/lang/String;)V
    //   1133: goto +16 -> 1149
    //   1136: aload_1
    //   1137: astore 5
    //   1139: aload 13
    //   1141: invokevirtual 52	java/lang/StringBuilder:toString	()Ljava/lang/String;
    //   1144: astore 7
    //   1146: goto -23 -> 1123
    //   1149: aload_1
    //   1150: astore 5
    //   1152: aload_1
    //   1153: aload_1
    //   1154: invokevirtual 144	java/nio/ByteBuffer:get	()B
    //   1157: sipush 255
    //   1160: iand
    //   1161: newarray <illegal type>
    //   1163: invokevirtual 192	java/nio/ByteBuffer:get	([B)Ljava/nio/ByteBuffer;
    //   1166: pop
    //   1167: aload_1
    //   1168: astore 5
    //   1170: aload_1
    //   1171: invokevirtual 144	java/nio/ByteBuffer:get	()B
    //   1174: iconst_1
    //   1175: if_icmpne +27 -> 1202
    //   1178: aload_1
    //   1179: astore 5
    //   1181: aload_1
    //   1182: invokevirtual 161	java/nio/ByteBuffer:getInt	()I
    //   1185: pop
    //   1186: aload_1
    //   1187: astore 5
    //   1189: aload_1
    //   1190: invokevirtual 161	java/nio/ByteBuffer:getInt	()I
    //   1193: pop
    //   1194: aload_1
    //   1195: astore 5
    //   1197: aload_1
    //   1198: invokevirtual 148	java/nio/ByteBuffer:getShort	()S
    //   1201: pop
    //   1202: aload_1
    //   1203: astore 5
    //   1205: aload_1
    //   1206: invokevirtual 144	java/nio/ByteBuffer:get	()B
    //   1209: iconst_1
    //   1210: if_icmpne +91 -> 1301
    //   1213: aload_1
    //   1214: astore 5
    //   1216: aload_1
    //   1217: invokevirtual 144	java/nio/ByteBuffer:get	()B
    //   1220: sipush 255
    //   1223: iand
    //   1224: newarray <illegal type>
    //   1226: astore 7
    //   1228: aload_1
    //   1229: astore 5
    //   1231: aload_1
    //   1232: aload 7
    //   1234: invokevirtual 192	java/nio/ByteBuffer:get	([B)Ljava/nio/ByteBuffer;
    //   1237: pop
    //   1238: aload_1
    //   1239: astore 5
    //   1241: aload 6
    //   1243: new 60	java/lang/String
    //   1246: dup
    //   1247: aload 7
    //   1249: ldc -62
    //   1251: invokespecial 197	java/lang/String:<init>	([BLjava/lang/String;)V
    //   1254: invokevirtual 278	com/amap/api/mapcore/util/le:setBuildingId	(Ljava/lang/String;)V
    //   1257: aload_1
    //   1258: astore 5
    //   1260: aload_1
    //   1261: invokevirtual 144	java/nio/ByteBuffer:get	()B
    //   1264: sipush 255
    //   1267: iand
    //   1268: newarray <illegal type>
    //   1270: astore 7
    //   1272: aload_1
    //   1273: astore 5
    //   1275: aload_1
    //   1276: aload 7
    //   1278: invokevirtual 192	java/nio/ByteBuffer:get	([B)Ljava/nio/ByteBuffer;
    //   1281: pop
    //   1282: aload_1
    //   1283: astore 5
    //   1285: aload 6
    //   1287: new 60	java/lang/String
    //   1290: dup
    //   1291: aload 7
    //   1293: ldc -62
    //   1295: invokespecial 197	java/lang/String:<init>	([BLjava/lang/String;)V
    //   1298: invokevirtual 281	com/amap/api/mapcore/util/le:setFloor	(Ljava/lang/String;)V
    //   1301: aload_1
    //   1302: astore 5
    //   1304: aload_1
    //   1305: invokevirtual 144	java/nio/ByteBuffer:get	()B
    //   1308: iconst_1
    //   1309: if_icmpne +27 -> 1336
    //   1312: aload_1
    //   1313: astore 5
    //   1315: aload_1
    //   1316: invokevirtual 144	java/nio/ByteBuffer:get	()B
    //   1319: pop
    //   1320: aload_1
    //   1321: astore 5
    //   1323: aload_1
    //   1324: invokevirtual 161	java/nio/ByteBuffer:getInt	()I
    //   1327: pop
    //   1328: aload_1
    //   1329: astore 5
    //   1331: aload_1
    //   1332: invokevirtual 144	java/nio/ByteBuffer:get	()B
    //   1335: pop
    //   1336: aload_1
    //   1337: astore 5
    //   1339: aload_1
    //   1340: invokevirtual 144	java/nio/ByteBuffer:get	()B
    //   1343: iconst_1
    //   1344: if_icmpne +15 -> 1359
    //   1347: aload_1
    //   1348: astore 5
    //   1350: aload 6
    //   1352: aload_1
    //   1353: invokevirtual 285	java/nio/ByteBuffer:getLong	()J
    //   1356: invokevirtual 289	com/amap/api/mapcore/util/le:setTime	(J)V
    //   1359: aload_1
    //   1360: astore 5
    //   1362: aload_1
    //   1363: invokevirtual 148	java/nio/ByteBuffer:getShort	()S
    //   1366: newarray <illegal type>
    //   1368: astore 7
    //   1370: aload_1
    //   1371: astore 5
    //   1373: aload_1
    //   1374: aload 7
    //   1376: invokevirtual 192	java/nio/ByteBuffer:get	([B)Ljava/nio/ByteBuffer;
    //   1379: pop
    //   1380: aload_1
    //   1381: astore 5
    //   1383: aload 6
    //   1385: new 60	java/lang/String
    //   1388: dup
    //   1389: aload 7
    //   1391: ldc -62
    //   1393: invokespecial 197	java/lang/String:<init>	([BLjava/lang/String;)V
    //   1396: invokevirtual 291	com/amap/api/mapcore/util/le:a	(Ljava/lang/String;)V
    //   1399: aload 6
    //   1401: astore 5
    //   1403: aload_1
    //   1404: ifnull +136 -> 1540
    //   1407: aload 6
    //   1409: astore 5
    //   1411: aload_1
    //   1412: invokevirtual 158	java/nio/ByteBuffer:clear	()Ljava/nio/Buffer;
    //   1415: pop
    //   1416: goto +124 -> 1540
    //   1419: astore 6
    //   1421: goto +14 -> 1435
    //   1424: astore_1
    //   1425: aconst_null
    //   1426: astore 5
    //   1428: goto +142 -> 1570
    //   1431: astore 6
    //   1433: aconst_null
    //   1434: astore_1
    //   1435: aload_1
    //   1436: astore 5
    //   1438: new 21	com/amap/api/mapcore/util/le
    //   1441: dup
    //   1442: ldc 23
    //   1444: invokespecial 26	com/amap/api/mapcore/util/le:<init>	(Ljava/lang/String;)V
    //   1447: astore 7
    //   1449: aload_1
    //   1450: astore 5
    //   1452: aload 7
    //   1454: iconst_5
    //   1455: invokevirtual 30	com/amap/api/mapcore/util/le:setErrorCode	(I)V
    //   1458: aload_1
    //   1459: astore 5
    //   1461: aload_0
    //   1462: getfield 15	com/amap/api/mapcore/util/kt:a	Ljava/lang/StringBuilder;
    //   1465: astore 8
    //   1467: aload_1
    //   1468: astore 5
    //   1470: new 12	java/lang/StringBuilder
    //   1473: dup
    //   1474: ldc_w 293
    //   1477: invokespecial 44	java/lang/StringBuilder:<init>	(Ljava/lang/String;)V
    //   1480: astore 9
    //   1482: aload_1
    //   1483: astore 5
    //   1485: aload 9
    //   1487: aload 6
    //   1489: invokevirtual 71	java/lang/Throwable:getMessage	()Ljava/lang/String;
    //   1492: invokevirtual 48	java/lang/StringBuilder:append	(Ljava/lang/String;)Ljava/lang/StringBuilder;
    //   1495: pop
    //   1496: aload_1
    //   1497: astore 5
    //   1499: aload 8
    //   1501: aload 9
    //   1503: invokevirtual 52	java/lang/StringBuilder:toString	()Ljava/lang/String;
    //   1506: invokevirtual 48	java/lang/StringBuilder:append	(Ljava/lang/String;)Ljava/lang/StringBuilder;
    //   1509: pop
    //   1510: aload_1
    //   1511: astore 5
    //   1513: aload 7
    //   1515: aload_0
    //   1516: getfield 15	com/amap/api/mapcore/util/kt:a	Ljava/lang/StringBuilder;
    //   1519: invokevirtual 52	java/lang/StringBuilder:toString	()Ljava/lang/String;
    //   1522: invokevirtual 124	com/amap/api/mapcore/util/le:setLocationDetail	(Ljava/lang/String;)V
    //   1525: aload 7
    //   1527: astore 5
    //   1529: aload_1
    //   1530: ifnull +10 -> 1540
    //   1533: aload 7
    //   1535: astore 5
    //   1537: goto -126 -> 1411
    //   1540: aload_0
    //   1541: getfield 15	com/amap/api/mapcore/util/kt:a	Ljava/lang/StringBuilder;
    //   1544: invokevirtual 128	java/lang/StringBuilder:length	()I
    //   1547: ifle +19 -> 1566
    //   1550: aload_0
    //   1551: getfield 15	com/amap/api/mapcore/util/kt:a	Ljava/lang/StringBuilder;
    //   1554: iconst_0
    //   1555: aload_0
    //   1556: getfield 15	com/amap/api/mapcore/util/kt:a	Ljava/lang/StringBuilder;
    //   1559: invokevirtual 128	java/lang/StringBuilder:length	()I
    //   1562: invokevirtual 132	java/lang/StringBuilder:delete	(II)Ljava/lang/StringBuilder;
    //   1565: pop
    //   1566: aload 5
    //   1568: areturn
    //   1569: astore_1
    //   1570: aload 5
    //   1572: ifnull +9 -> 1581
    //   1575: aload 5
    //   1577: invokevirtual 158	java/nio/ByteBuffer:clear	()Ljava/nio/Buffer;
    //   1580: pop
    //   1581: aload_1
    //   1582: athrow
    //   1583: astore 5
    //   1585: goto -1303 -> 282
    //   1588: astore 5
    //   1590: goto -1254 -> 336
    //   1593: astore 5
    //   1595: goto -1255 -> 340
    //   1598: astore 5
    //   1600: goto -1206 -> 394
    //   1603: astore 5
    //   1605: goto -1207 -> 398
    //   1608: astore 5
    //   1610: goto -1158 -> 452
    //   1613: astore 5
    //   1615: goto -1159 -> 456
    //   1618: astore 5
    //   1620: goto -1100 -> 520
    //   1623: astore 5
    //   1625: goto -1101 -> 524
    //   1628: astore 5
    //   1630: goto -1062 -> 568
    //   1633: astore 5
    //   1635: goto -1013 -> 622
    //   1638: astore 5
    //   1640: goto -1014 -> 626
    //   1643: astore 5
    //   1645: goto -975 -> 670
    //   1648: astore 5
    //   1650: goto -926 -> 724
    //   1653: astore 5
    //   1655: goto -927 -> 728
    //   1658: astore 5
    //   1660: goto -888 -> 772
    //   1663: astore 5
    //   1665: goto -408 -> 1257
    //   1668: astore 5
    //   1670: goto -369 -> 1301
    //   1673: astore 5
    //   1675: goto -276 -> 1399
    // Local variable table:
    //   start	length	slot	name	signature
    //   0	1678	0	this	kt
    //   0	1678	1	paramArrayOfByte	byte[]
    //   124	54	2	d	double
    //   119	39	4	i	int
    //   68	1508	5	localObject1	Object
    //   1583	1	5	localThrowable1	Throwable
    //   1588	1	5	localThrowable2	Throwable
    //   1593	1	5	localThrowable3	Throwable
    //   1598	1	5	localThrowable4	Throwable
    //   1603	1	5	localThrowable5	Throwable
    //   1608	1	5	localThrowable6	Throwable
    //   1613	1	5	localThrowable7	Throwable
    //   1618	1	5	localThrowable8	Throwable
    //   1623	1	5	localThrowable9	Throwable
    //   1628	1	5	localThrowable10	Throwable
    //   1633	1	5	localThrowable11	Throwable
    //   1638	1	5	localThrowable12	Throwable
    //   1643	1	5	localThrowable13	Throwable
    //   1648	1	5	localThrowable14	Throwable
    //   1653	1	5	localThrowable15	Throwable
    //   1658	1	5	localThrowable16	Throwable
    //   1663	1	5	localThrowable17	Throwable
    //   1668	1	5	localThrowable18	Throwable
    //   1673	1	5	localThrowable19	Throwable
    //   9	1399	6	localle	le
    //   1419	1	6	localThrowable20	Throwable
    //   1431	57	6	localThrowable21	Throwable
    //   251	1283	7	localObject2	Object
    //   353	1147	8	localObject3	Object
    //   411	1091	9	localObject4	Object
    //   469	457	10	localObject5	Object
    //   537	444	11	localObject6	Object
    //   639	318	12	localObject7	Object
    //   741	399	13	localObject8	Object
    // Exception table:
    //   from	to	target	type
    //   70	77	1419	java/lang/Throwable
    //   80	92	1419	java/lang/Throwable
    //   95	100	1419	java/lang/Throwable
    //   115	121	1419	java/lang/Throwable
    //   139	148	1419	java/lang/Throwable
    //   151	157	1419	java/lang/Throwable
    //   175	184	1419	java/lang/Throwable
    //   187	197	1419	java/lang/Throwable
    //   200	212	1419	java/lang/Throwable
    //   215	227	1419	java/lang/Throwable
    //   230	238	1419	java/lang/Throwable
    //   241	253	1419	java/lang/Throwable
    //   256	263	1419	java/lang/Throwable
    //   285	297	1419	java/lang/Throwable
    //   300	307	1419	java/lang/Throwable
    //   343	355	1419	java/lang/Throwable
    //   358	365	1419	java/lang/Throwable
    //   401	413	1419	java/lang/Throwable
    //   416	423	1419	java/lang/Throwable
    //   459	471	1419	java/lang/Throwable
    //   474	481	1419	java/lang/Throwable
    //   527	539	1419	java/lang/Throwable
    //   542	549	1419	java/lang/Throwable
    //   571	583	1419	java/lang/Throwable
    //   586	593	1419	java/lang/Throwable
    //   629	641	1419	java/lang/Throwable
    //   644	651	1419	java/lang/Throwable
    //   673	685	1419	java/lang/Throwable
    //   688	695	1419	java/lang/Throwable
    //   731	743	1419	java/lang/Throwable
    //   746	753	1419	java/lang/Throwable
    //   775	784	1419	java/lang/Throwable
    //   787	795	1419	java/lang/Throwable
    //   798	806	1419	java/lang/Throwable
    //   809	817	1419	java/lang/Throwable
    //   820	828	1419	java/lang/Throwable
    //   831	841	1419	java/lang/Throwable
    //   844	854	1419	java/lang/Throwable
    //   857	865	1419	java/lang/Throwable
    //   868	876	1419	java/lang/Throwable
    //   879	887	1419	java/lang/Throwable
    //   890	898	1419	java/lang/Throwable
    //   901	909	1419	java/lang/Throwable
    //   912	920	1419	java/lang/Throwable
    //   923	931	1419	java/lang/Throwable
    //   934	942	1419	java/lang/Throwable
    //   945	953	1419	java/lang/Throwable
    //   956	964	1419	java/lang/Throwable
    //   967	975	1419	java/lang/Throwable
    //   978	986	1419	java/lang/Throwable
    //   989	997	1419	java/lang/Throwable
    //   1000	1009	1419	java/lang/Throwable
    //   1012	1024	1419	java/lang/Throwable
    //   1027	1039	1419	java/lang/Throwable
    //   1042	1054	1419	java/lang/Throwable
    //   1057	1064	1419	java/lang/Throwable
    //   1067	1077	1419	java/lang/Throwable
    //   1080	1087	1419	java/lang/Throwable
    //   1095	1106	1419	java/lang/Throwable
    //   1109	1123	1419	java/lang/Throwable
    //   1126	1133	1419	java/lang/Throwable
    //   1139	1146	1419	java/lang/Throwable
    //   1152	1167	1419	java/lang/Throwable
    //   1170	1178	1419	java/lang/Throwable
    //   1181	1186	1419	java/lang/Throwable
    //   1189	1194	1419	java/lang/Throwable
    //   1197	1202	1419	java/lang/Throwable
    //   1205	1213	1419	java/lang/Throwable
    //   1216	1228	1419	java/lang/Throwable
    //   1231	1238	1419	java/lang/Throwable
    //   1260	1272	1419	java/lang/Throwable
    //   1275	1282	1419	java/lang/Throwable
    //   1304	1312	1419	java/lang/Throwable
    //   1315	1320	1419	java/lang/Throwable
    //   1323	1328	1419	java/lang/Throwable
    //   1331	1336	1419	java/lang/Throwable
    //   1339	1347	1419	java/lang/Throwable
    //   1350	1359	1419	java/lang/Throwable
    //   1362	1370	1419	java/lang/Throwable
    //   1373	1380	1419	java/lang/Throwable
    //   0	11	1424	finally
    //   15	59	1424	finally
    //   62	67	1424	finally
    //   0	11	1431	java/lang/Throwable
    //   15	59	1431	java/lang/Throwable
    //   62	67	1431	java/lang/Throwable
    //   70	77	1569	finally
    //   80	92	1569	finally
    //   95	100	1569	finally
    //   115	121	1569	finally
    //   139	148	1569	finally
    //   151	157	1569	finally
    //   175	184	1569	finally
    //   187	197	1569	finally
    //   200	212	1569	finally
    //   215	227	1569	finally
    //   230	238	1569	finally
    //   241	253	1569	finally
    //   256	263	1569	finally
    //   266	282	1569	finally
    //   285	297	1569	finally
    //   300	307	1569	finally
    //   310	323	1569	finally
    //   326	333	1569	finally
    //   343	355	1569	finally
    //   358	365	1569	finally
    //   368	381	1569	finally
    //   384	391	1569	finally
    //   401	413	1569	finally
    //   416	423	1569	finally
    //   426	439	1569	finally
    //   442	449	1569	finally
    //   459	471	1569	finally
    //   474	481	1569	finally
    //   484	497	1569	finally
    //   500	507	1569	finally
    //   510	517	1569	finally
    //   527	539	1569	finally
    //   542	549	1569	finally
    //   552	568	1569	finally
    //   571	583	1569	finally
    //   586	593	1569	finally
    //   596	609	1569	finally
    //   612	619	1569	finally
    //   629	641	1569	finally
    //   644	651	1569	finally
    //   654	670	1569	finally
    //   673	685	1569	finally
    //   688	695	1569	finally
    //   698	711	1569	finally
    //   714	721	1569	finally
    //   731	743	1569	finally
    //   746	753	1569	finally
    //   756	772	1569	finally
    //   775	784	1569	finally
    //   787	795	1569	finally
    //   798	806	1569	finally
    //   809	817	1569	finally
    //   820	828	1569	finally
    //   831	841	1569	finally
    //   844	854	1569	finally
    //   857	865	1569	finally
    //   868	876	1569	finally
    //   879	887	1569	finally
    //   890	898	1569	finally
    //   901	909	1569	finally
    //   912	920	1569	finally
    //   923	931	1569	finally
    //   934	942	1569	finally
    //   945	953	1569	finally
    //   956	964	1569	finally
    //   967	975	1569	finally
    //   978	986	1569	finally
    //   989	997	1569	finally
    //   1000	1009	1569	finally
    //   1012	1024	1569	finally
    //   1027	1039	1569	finally
    //   1042	1054	1569	finally
    //   1057	1064	1569	finally
    //   1067	1077	1569	finally
    //   1080	1087	1569	finally
    //   1095	1106	1569	finally
    //   1109	1123	1569	finally
    //   1126	1133	1569	finally
    //   1139	1146	1569	finally
    //   1152	1167	1569	finally
    //   1170	1178	1569	finally
    //   1181	1186	1569	finally
    //   1189	1194	1569	finally
    //   1197	1202	1569	finally
    //   1205	1213	1569	finally
    //   1216	1228	1569	finally
    //   1231	1238	1569	finally
    //   1241	1257	1569	finally
    //   1260	1272	1569	finally
    //   1275	1282	1569	finally
    //   1285	1301	1569	finally
    //   1304	1312	1569	finally
    //   1315	1320	1569	finally
    //   1323	1328	1569	finally
    //   1331	1336	1569	finally
    //   1339	1347	1569	finally
    //   1350	1359	1569	finally
    //   1362	1370	1569	finally
    //   1373	1380	1569	finally
    //   1383	1399	1569	finally
    //   1438	1449	1569	finally
    //   1452	1458	1569	finally
    //   1461	1467	1569	finally
    //   1470	1482	1569	finally
    //   1485	1496	1569	finally
    //   1499	1510	1569	finally
    //   1513	1525	1569	finally
    //   266	282	1583	java/lang/Throwable
    //   310	323	1588	java/lang/Throwable
    //   326	333	1593	java/lang/Throwable
    //   368	381	1598	java/lang/Throwable
    //   384	391	1603	java/lang/Throwable
    //   426	439	1608	java/lang/Throwable
    //   442	449	1613	java/lang/Throwable
    //   484	497	1618	java/lang/Throwable
    //   500	507	1623	java/lang/Throwable
    //   510	517	1623	java/lang/Throwable
    //   552	568	1628	java/lang/Throwable
    //   596	609	1633	java/lang/Throwable
    //   612	619	1638	java/lang/Throwable
    //   654	670	1643	java/lang/Throwable
    //   698	711	1648	java/lang/Throwable
    //   714	721	1653	java/lang/Throwable
    //   756	772	1658	java/lang/Throwable
    //   1241	1257	1663	java/lang/Throwable
    //   1285	1301	1668	java/lang/Throwable
    //   1383	1399	1673	java/lang/Throwable
  }
}


/* Location:              C:\Users\lixia\Desktop\android反编译三件套\dex2jar-2.0\classes-dex2jar.jar!\com\amap\api\mapcore\util\kt.class
 * Java compiler version: 6 (50.0)
 * JD-Core Version:       0.7.1
 */